package cmcm.com.myapplication;

import android.content.ContentResolver;
import android.content.ContentValues;
import android.content.Context;
import java.util.List;

public class kl
{
  private static kl a;

  public static kl a()
  {
    if (a == null)
      a = new kl();
    return a;
  }

  private void a(Context paramContext, String[] paramArrayOfString)
  {
    StringBuilder localStringBuilder = new StringBuilder();
    int i = 0;
    while (i < paramArrayOfString.length)
    {
      if (i != 0)
        localStringBuilder.append(",");
      localStringBuilder.append("?");
      i += 1;
    }
    if (kn.a)
      kx.a("DF_SQL", "process....... " + localStringBuilder);
    paramContext.getContentResolver().delete(kd.a, "ID in (" + localStringBuilder.toString() + ")", paramArrayOfString);
  }

  private boolean a(String paramString)
  {
    if ((paramString.contentEquals(" ")) || (paramString.contentEquals("Exception")) || (paramString.length() > 10));
    for (int i = 1; i == 0; i = 0)
      return true;
    return false;
  }

  // ERROR //
  private boolean b(Context paramContext, String paramString, long paramLong)
  {
    // Byte code:
    //   0: aconst_null
    //   1: astore 5
    //   3: iconst_0
    //   4: istore 7
    //   6: aload_0
    //   7: monitorenter
    //   8: aload_0
    //   9: aload_2
    //   10: invokespecial 90	kl:a	(Ljava/lang/String;)Z
    //   13: istore 8
    //   15: iload 8
    //   17: ifne +8 -> 25
    //   20: aload_0
    //   21: monitorexit
    //   22: iload 7
    //   24: ireturn
    //   25: aload_1
    //   26: invokevirtual 54	android/content/Context:getContentResolver	()Landroid/content/ContentResolver;
    //   29: getstatic 59	kd:a	Landroid/net/Uri;
    //   32: iconst_1
    //   33: anewarray 74	java/lang/String
    //   36: dup
    //   37: iconst_0
    //   38: ldc 92
    //   40: aastore
    //   41: ldc 94
    //   43: iconst_2
    //   44: anewarray 74	java/lang/String
    //   47: dup
    //   48: iconst_0
    //   49: aload_2
    //   50: aastore
    //   51: dup
    //   52: iconst_1
    //   53: lload_3
    //   54: invokestatic 98	java/lang/String:valueOf	(J)Ljava/lang/String;
    //   57: aastore
    //   58: aconst_null
    //   59: invokevirtual 102	android/content/ContentResolver:query	(Landroid/net/Uri;[Ljava/lang/String;Ljava/lang/String;[Ljava/lang/String;Ljava/lang/String;)Landroid/database/Cursor;
    //   62: astore_2
    //   63: aload_2
    //   64: ifnull +120 -> 184
    //   67: aload_2
    //   68: astore_1
    //   69: aload_2
    //   70: invokeinterface 108 1 0
    //   75: ifeq +109 -> 184
    //   78: aload_2
    //   79: astore_1
    //   80: aload_2
    //   81: iconst_0
    //   82: invokeinterface 112 2 0
    //   87: istore 6
    //   89: iload 6
    //   91: iconst_1
    //   92: if_icmplt +92 -> 184
    //   95: iconst_1
    //   96: istore 8
    //   98: iload 8
    //   100: istore 7
    //   102: aload_2
    //   103: ifnull +13 -> 116
    //   106: aload_2
    //   107: invokeinterface 115 1 0
    //   112: iload 8
    //   114: istore 7
    //   116: goto -96 -> 20
    //   119: astore 5
    //   121: aconst_null
    //   122: astore_2
    //   123: aload_2
    //   124: astore_1
    //   125: aload 5
    //   127: invokevirtual 118	java/lang/Exception:printStackTrace	()V
    //   130: aload_2
    //   131: ifnull +47 -> 178
    //   134: aload_2
    //   135: invokeinterface 115 1 0
    //   140: iconst_0
    //   141: istore 7
    //   143: goto -27 -> 116
    //   146: aload_2
    //   147: ifnull +9 -> 156
    //   150: aload_2
    //   151: invokeinterface 115 1 0
    //   156: aload_1
    //   157: athrow
    //   158: astore_1
    //   159: aload_0
    //   160: monitorexit
    //   161: aload_1
    //   162: athrow
    //   163: astore 5
    //   165: aload_1
    //   166: astore_2
    //   167: aload 5
    //   169: astore_1
    //   170: goto -24 -> 146
    //   173: astore 5
    //   175: goto -52 -> 123
    //   178: iconst_0
    //   179: istore 7
    //   181: goto -65 -> 116
    //   184: iconst_0
    //   185: istore 8
    //   187: goto -89 -> 98
    //   190: astore_1
    //   191: aload 5
    //   193: astore_2
    //   194: goto -48 -> 146
    //
    // Exception table:
    //   from	to	target	type
    //   25	63	119	java/lang/Exception
    //   8	15	158	finally
    //   106	112	158	finally
    //   134	140	158	finally
    //   150	156	158	finally
    //   156	158	158	finally
    //   69	78	163	finally
    //   80	89	163	finally
    //   125	130	163	finally
    //   69	78	173	java/lang/Exception
    //   80	89	173	java/lang/Exception
    //   25	63	190	finally
  }

  // ERROR //
  private boolean b(Context paramContext, String paramString1, String paramString2)
  {
    // Byte code:
    //   0: aconst_null
    //   1: astore 4
    //   3: iconst_0
    //   4: istore 6
    //   6: aload_0
    //   7: monitorenter
    //   8: aload_0
    //   9: aload_2
    //   10: invokespecial 90	kl:a	(Ljava/lang/String;)Z
    //   13: istore 7
    //   15: iload 7
    //   17: ifne +8 -> 25
    //   20: aload_0
    //   21: monitorexit
    //   22: iload 6
    //   24: ireturn
    //   25: aload_1
    //   26: invokevirtual 54	android/content/Context:getContentResolver	()Landroid/content/ContentResolver;
    //   29: getstatic 59	kd:a	Landroid/net/Uri;
    //   32: iconst_1
    //   33: anewarray 74	java/lang/String
    //   36: dup
    //   37: iconst_0
    //   38: ldc 92
    //   40: aastore
    //   41: ldc 121
    //   43: iconst_2
    //   44: anewarray 74	java/lang/String
    //   47: dup
    //   48: iconst_0
    //   49: aload_2
    //   50: aastore
    //   51: dup
    //   52: iconst_1
    //   53: aload_3
    //   54: aastore
    //   55: aconst_null
    //   56: invokevirtual 102	android/content/ContentResolver:query	(Landroid/net/Uri;[Ljava/lang/String;Ljava/lang/String;[Ljava/lang/String;Ljava/lang/String;)Landroid/database/Cursor;
    //   59: astore_2
    //   60: aload_2
    //   61: ifnull +115 -> 176
    //   64: aload_2
    //   65: astore_1
    //   66: aload_2
    //   67: invokeinterface 108 1 0
    //   72: ifeq +104 -> 176
    //   75: aload_2
    //   76: astore_1
    //   77: aload_2
    //   78: iconst_0
    //   79: invokeinterface 112 2 0
    //   84: istore 5
    //   86: iload 5
    //   88: iconst_1
    //   89: if_icmplt +87 -> 176
    //   92: iconst_1
    //   93: istore 7
    //   95: iload 7
    //   97: istore 6
    //   99: aload_2
    //   100: ifnull +13 -> 113
    //   103: aload_2
    //   104: invokeinterface 115 1 0
    //   109: iload 7
    //   111: istore 6
    //   113: goto -93 -> 20
    //   116: astore_3
    //   117: aconst_null
    //   118: astore_2
    //   119: aload_2
    //   120: astore_1
    //   121: aload_3
    //   122: invokevirtual 118	java/lang/Exception:printStackTrace	()V
    //   125: aload_2
    //   126: ifnull +44 -> 170
    //   129: aload_2
    //   130: invokeinterface 115 1 0
    //   135: iconst_0
    //   136: istore 6
    //   138: goto -25 -> 113
    //   141: aload_2
    //   142: ifnull +9 -> 151
    //   145: aload_2
    //   146: invokeinterface 115 1 0
    //   151: aload_1
    //   152: athrow
    //   153: astore_1
    //   154: aload_0
    //   155: monitorexit
    //   156: aload_1
    //   157: athrow
    //   158: astore_3
    //   159: aload_1
    //   160: astore_2
    //   161: aload_3
    //   162: astore_1
    //   163: goto -22 -> 141
    //   166: astore_3
    //   167: goto -48 -> 119
    //   170: iconst_0
    //   171: istore 6
    //   173: goto -60 -> 113
    //   176: iconst_0
    //   177: istore 7
    //   179: goto -84 -> 95
    //   182: astore_1
    //   183: aload 4
    //   185: astore_2
    //   186: goto -45 -> 141
    //
    // Exception table:
    //   from	to	target	type
    //   25	60	116	java/lang/Exception
    //   8	15	153	finally
    //   103	109	153	finally
    //   129	135	153	finally
    //   145	151	153	finally
    //   151	153	153	finally
    //   66	75	158	finally
    //   77	86	158	finally
    //   121	125	158	finally
    //   66	75	166	java/lang/Exception
    //   77	86	166	java/lang/Exception
    //   25	60	182	finally
  }

  // ERROR //
  private int c(Context paramContext, String paramString, long paramLong)
  {
    // Byte code:
    //   0: aconst_null
    //   1: astore 6
    //   3: aload_0
    //   4: monitorenter
    //   5: aload_0
    //   6: aload_2
    //   7: invokespecial 90	kl:a	(Ljava/lang/String;)Z
    //   10: istore 10
    //   12: iload 10
    //   14: ifne +11 -> 25
    //   17: iconst_0
    //   18: istore 7
    //   20: aload_0
    //   21: monitorexit
    //   22: iload 7
    //   24: ireturn
    //   25: aload_1
    //   26: invokevirtual 54	android/content/Context:getContentResolver	()Landroid/content/ContentResolver;
    //   29: getstatic 59	kd:a	Landroid/net/Uri;
    //   32: iconst_1
    //   33: anewarray 74	java/lang/String
    //   36: dup
    //   37: iconst_0
    //   38: ldc 125
    //   40: aastore
    //   41: ldc 94
    //   43: iconst_2
    //   44: anewarray 74	java/lang/String
    //   47: dup
    //   48: iconst_0
    //   49: aload_2
    //   50: aastore
    //   51: dup
    //   52: iconst_1
    //   53: lload_3
    //   54: invokestatic 98	java/lang/String:valueOf	(J)Ljava/lang/String;
    //   57: aastore
    //   58: aconst_null
    //   59: invokevirtual 102	android/content/ContentResolver:query	(Landroid/net/Uri;[Ljava/lang/String;Ljava/lang/String;[Ljava/lang/String;Ljava/lang/String;)Landroid/database/Cursor;
    //   62: astore 5
    //   64: aload 5
    //   66: ifnull +17 -> 83
    //   69: aload 5
    //   71: invokeinterface 128 1 0
    //   76: istore 7
    //   78: iload 7
    //   80: ifne +21 -> 101
    //   83: aload 5
    //   85: ifnull +10 -> 95
    //   88: aload 5
    //   90: invokeinterface 115 1 0
    //   95: iconst_0
    //   96: istore 7
    //   98: goto -78 -> 20
    //   101: iconst_0
    //   102: istore 8
    //   104: iconst_0
    //   105: istore 7
    //   107: aload 5
    //   109: invokeinterface 131 1 0
    //   114: ifeq +34 -> 148
    //   117: aload 5
    //   119: aload 5
    //   121: ldc 125
    //   123: invokeinterface 135 2 0
    //   128: invokeinterface 112 2 0
    //   133: istore 9
    //   135: iload 8
    //   137: iconst_1
    //   138: iadd
    //   139: istore 8
    //   141: iload 9
    //   143: istore 7
    //   145: goto -38 -> 107
    //   148: iload 8
    //   150: iconst_1
    //   151: if_icmple +122 -> 273
    //   154: aload_0
    //   155: aload_1
    //   156: aload_2
    //   157: invokevirtual 138	kl:a	(Landroid/content/Context;Ljava/lang/String;)Z
    //   160: pop
    //   161: iconst_0
    //   162: istore 8
    //   164: iload 8
    //   166: istore 7
    //   168: aload 5
    //   170: ifnull -150 -> 20
    //   173: aload 5
    //   175: invokeinterface 115 1 0
    //   180: iload 8
    //   182: istore 7
    //   184: goto -164 -> 20
    //   187: astore_1
    //   188: aload_0
    //   189: monitorexit
    //   190: aload_1
    //   191: athrow
    //   192: astore_2
    //   193: aconst_null
    //   194: astore_1
    //   195: iconst_0
    //   196: istore 8
    //   198: aload_2
    //   199: invokevirtual 118	java/lang/Exception:printStackTrace	()V
    //   202: iload 8
    //   204: istore 7
    //   206: aload_1
    //   207: ifnull -187 -> 20
    //   210: aload_1
    //   211: invokeinterface 115 1 0
    //   216: iload 8
    //   218: istore 7
    //   220: goto -200 -> 20
    //   223: aload_2
    //   224: ifnull +9 -> 233
    //   227: aload_2
    //   228: invokeinterface 115 1 0
    //   233: aload_1
    //   234: athrow
    //   235: astore_1
    //   236: aload 5
    //   238: astore_2
    //   239: goto -16 -> 223
    //   242: astore 5
    //   244: aload_1
    //   245: astore_2
    //   246: aload 5
    //   248: astore_1
    //   249: goto -26 -> 223
    //   252: astore_2
    //   253: aload 5
    //   255: astore_1
    //   256: iconst_0
    //   257: istore 8
    //   259: goto -61 -> 198
    //   262: astore_2
    //   263: aload 5
    //   265: astore_1
    //   266: iload 7
    //   268: istore 8
    //   270: goto -72 -> 198
    //   273: iload 7
    //   275: istore 8
    //   277: goto -113 -> 164
    //   280: astore_1
    //   281: aload 6
    //   283: astore_2
    //   284: goto -61 -> 223
    //
    // Exception table:
    //   from	to	target	type
    //   5	12	187	finally
    //   88	95	187	finally
    //   173	180	187	finally
    //   210	216	187	finally
    //   227	233	187	finally
    //   233	235	187	finally
    //   25	64	192	java/lang/Exception
    //   69	78	235	finally
    //   107	135	235	finally
    //   154	161	235	finally
    //   198	202	242	finally
    //   69	78	252	java/lang/Exception
    //   107	135	262	java/lang/Exception
    //   154	161	262	java/lang/Exception
    //   25	64	280	finally
  }

  // ERROR //
  List<kw> a(Context paramContext, int paramInt)
  {
    // Byte code:
    //   0: aload_0
    //   1: monitorenter
    //   2: new 141	java/util/ArrayList
    //   5: dup
    //   6: invokespecial 142	java/util/ArrayList:<init>	()V
    //   9: astore 5
    //   11: aload_1
    //   12: invokevirtual 54	android/content/Context:getContentResolver	()Landroid/content/ContentResolver;
    //   15: getstatic 59	kd:a	Landroid/net/Uri;
    //   18: aconst_null
    //   19: ldc 144
    //   21: iconst_2
    //   22: anewarray 74	java/lang/String
    //   25: dup
    //   26: iconst_0
    //   27: iload_2
    //   28: invokestatic 147	java/lang/String:valueOf	(I)Ljava/lang/String;
    //   31: aastore
    //   32: dup
    //   33: iconst_1
    //   34: iconst_0
    //   35: invokestatic 147	java/lang/String:valueOf	(I)Ljava/lang/String;
    //   38: aastore
    //   39: aconst_null
    //   40: invokevirtual 102	android/content/ContentResolver:query	(Landroid/net/Uri;[Ljava/lang/String;Ljava/lang/String;[Ljava/lang/String;Ljava/lang/String;)Landroid/database/Cursor;
    //   43: astore_3
    //   44: aload_3
    //   45: ifnull +16 -> 61
    //   48: aload_3
    //   49: astore_1
    //   50: aload_3
    //   51: invokeinterface 128 1 0
    //   56: istore_2
    //   57: iload_2
    //   58: ifne +18 -> 76
    //   61: aload_3
    //   62: ifnull +9 -> 71
    //   65: aload_3
    //   66: invokeinterface 115 1 0
    //   71: aload_0
    //   72: monitorexit
    //   73: aload 5
    //   75: areturn
    //   76: aload_3
    //   77: astore_1
    //   78: aload_3
    //   79: invokeinterface 131 1 0
    //   84: ifeq +223 -> 307
    //   87: aload_3
    //   88: astore_1
    //   89: aload_3
    //   90: aload_3
    //   91: ldc 149
    //   93: invokeinterface 135 2 0
    //   98: invokeinterface 153 2 0
    //   103: lstore 8
    //   105: aload_3
    //   106: astore_1
    //   107: new 18	java/lang/StringBuilder
    //   110: dup
    //   111: invokespecial 19	java/lang/StringBuilder:<init>	()V
    //   114: ldc 155
    //   116: invokevirtual 25	java/lang/StringBuilder:append	(Ljava/lang/String;)Ljava/lang/StringBuilder;
    //   119: aload_3
    //   120: aload_3
    //   121: ldc 157
    //   123: invokeinterface 135 2 0
    //   128: invokeinterface 160 2 0
    //   133: invokevirtual 25	java/lang/StringBuilder:append	(Ljava/lang/String;)Ljava/lang/StringBuilder;
    //   136: invokevirtual 43	java/lang/StringBuilder:toString	()Ljava/lang/String;
    //   139: astore 4
    //   141: aload_3
    //   142: astore_1
    //   143: aload_3
    //   144: aload_3
    //   145: ldc 162
    //   147: invokeinterface 135 2 0
    //   152: invokeinterface 112 2 0
    //   157: istore_2
    //   158: aload_3
    //   159: astore_1
    //   160: new 18	java/lang/StringBuilder
    //   163: dup
    //   164: invokespecial 19	java/lang/StringBuilder:<init>	()V
    //   167: ldc 155
    //   169: invokevirtual 25	java/lang/StringBuilder:append	(Ljava/lang/String;)Ljava/lang/StringBuilder;
    //   172: aload_3
    //   173: aload_3
    //   174: ldc 164
    //   176: invokeinterface 135 2 0
    //   181: invokeinterface 160 2 0
    //   186: invokevirtual 25	java/lang/StringBuilder:append	(Ljava/lang/String;)Ljava/lang/StringBuilder;
    //   189: invokevirtual 43	java/lang/StringBuilder:toString	()Ljava/lang/String;
    //   192: astore 6
    //   194: aload_3
    //   195: astore_1
    //   196: aload_3
    //   197: aload_3
    //   198: ldc 125
    //   200: invokeinterface 135 2 0
    //   205: invokeinterface 153 2 0
    //   210: lstore 10
    //   212: aload_3
    //   213: astore_1
    //   214: new 166	kw
    //   217: dup
    //   218: invokespecial 167	kw:<init>	()V
    //   221: astore 7
    //   223: aload_3
    //   224: astore_1
    //   225: aload 7
    //   227: lload 8
    //   229: invokestatic 172	java/lang/Long:valueOf	(J)Ljava/lang/Long;
    //   232: invokevirtual 175	kw:a	(Ljava/lang/Long;)V
    //   235: aload_3
    //   236: astore_1
    //   237: aload 7
    //   239: aload 4
    //   241: invokevirtual 178	kw:a	(Ljava/lang/String;)V
    //   244: aload_3
    //   245: astore_1
    //   246: aload 7
    //   248: aload 6
    //   250: invokevirtual 180	kw:b	(Ljava/lang/String;)V
    //   253: aload_3
    //   254: astore_1
    //   255: aload 7
    //   257: iload_2
    //   258: invokevirtual 183	kw:a	(I)V
    //   261: aload_3
    //   262: astore_1
    //   263: aload 7
    //   265: lload 10
    //   267: invokevirtual 186	kw:a	(J)V
    //   270: aload_3
    //   271: astore_1
    //   272: aload 5
    //   274: aload 7
    //   276: invokeinterface 192 2 0
    //   281: pop
    //   282: goto -206 -> 76
    //   285: astore 4
    //   287: aload_3
    //   288: astore_1
    //   289: aload 4
    //   291: invokevirtual 118	java/lang/Exception:printStackTrace	()V
    //   294: aload_3
    //   295: ifnull +56 -> 351
    //   298: aload_3
    //   299: invokeinterface 115 1 0
    //   304: goto +47 -> 351
    //   307: aload_3
    //   308: ifnull +43 -> 351
    //   311: aload_3
    //   312: invokeinterface 115 1 0
    //   317: goto +34 -> 351
    //   320: astore_1
    //   321: aload_0
    //   322: monitorexit
    //   323: aload_1
    //   324: athrow
    //   325: astore_3
    //   326: aconst_null
    //   327: astore_1
    //   328: aload_1
    //   329: ifnull +9 -> 338
    //   332: aload_1
    //   333: invokeinterface 115 1 0
    //   338: aload_3
    //   339: athrow
    //   340: astore_3
    //   341: goto -13 -> 328
    //   344: astore 4
    //   346: aconst_null
    //   347: astore_3
    //   348: goto -61 -> 287
    //   351: goto -280 -> 71
    //
    // Exception table:
    //   from	to	target	type
    //   50	57	285	java/lang/Exception
    //   78	87	285	java/lang/Exception
    //   89	105	285	java/lang/Exception
    //   107	141	285	java/lang/Exception
    //   143	158	285	java/lang/Exception
    //   160	194	285	java/lang/Exception
    //   196	212	285	java/lang/Exception
    //   214	223	285	java/lang/Exception
    //   225	235	285	java/lang/Exception
    //   237	244	285	java/lang/Exception
    //   246	253	285	java/lang/Exception
    //   255	261	285	java/lang/Exception
    //   263	270	285	java/lang/Exception
    //   272	282	285	java/lang/Exception
    //   2	11	320	finally
    //   65	71	320	finally
    //   298	304	320	finally
    //   311	317	320	finally
    //   332	338	320	finally
    //   338	340	320	finally
    //   11	44	325	finally
    //   50	57	340	finally
    //   78	87	340	finally
    //   89	105	340	finally
    //   107	141	340	finally
    //   143	158	340	finally
    //   160	194	340	finally
    //   196	212	340	finally
    //   214	223	340	finally
    //   225	235	340	finally
    //   237	244	340	finally
    //   246	253	340	finally
    //   255	261	340	finally
    //   263	270	340	finally
    //   272	282	340	finally
    //   289	294	340	finally
    //   11	44	344	java/lang/Exception
  }

  // ERROR //
  List<kw> a(Context paramContext, int paramInt, String paramString)
  {
    // Byte code:
    //   0: aload_0
    //   1: monitorenter
    //   2: new 141	java/util/ArrayList
    //   5: dup
    //   6: invokespecial 142	java/util/ArrayList:<init>	()V
    //   9: astore 5
    //   11: aload_1
    //   12: invokevirtual 54	android/content/Context:getContentResolver	()Landroid/content/ContentResolver;
    //   15: getstatic 59	kd:a	Landroid/net/Uri;
    //   18: aconst_null
    //   19: ldc 197
    //   21: iconst_2
    //   22: anewarray 74	java/lang/String
    //   25: dup
    //   26: iconst_0
    //   27: iload_2
    //   28: invokestatic 147	java/lang/String:valueOf	(I)Ljava/lang/String;
    //   31: aastore
    //   32: dup
    //   33: iconst_1
    //   34: aload_3
    //   35: aastore
    //   36: aconst_null
    //   37: invokevirtual 102	android/content/ContentResolver:query	(Landroid/net/Uri;[Ljava/lang/String;Ljava/lang/String;[Ljava/lang/String;Ljava/lang/String;)Landroid/database/Cursor;
    //   40: astore_3
    //   41: aload_3
    //   42: ifnull +16 -> 58
    //   45: aload_3
    //   46: astore_1
    //   47: aload_3
    //   48: invokeinterface 128 1 0
    //   53: istore_2
    //   54: iload_2
    //   55: ifne +18 -> 73
    //   58: aload_3
    //   59: ifnull +9 -> 68
    //   62: aload_3
    //   63: invokeinterface 115 1 0
    //   68: aload_0
    //   69: monitorexit
    //   70: aload 5
    //   72: areturn
    //   73: aload_3
    //   74: astore_1
    //   75: aload_3
    //   76: invokeinterface 131 1 0
    //   81: ifeq +223 -> 304
    //   84: aload_3
    //   85: astore_1
    //   86: aload_3
    //   87: aload_3
    //   88: ldc 149
    //   90: invokeinterface 135 2 0
    //   95: invokeinterface 153 2 0
    //   100: lstore 8
    //   102: aload_3
    //   103: astore_1
    //   104: new 18	java/lang/StringBuilder
    //   107: dup
    //   108: invokespecial 19	java/lang/StringBuilder:<init>	()V
    //   111: ldc 155
    //   113: invokevirtual 25	java/lang/StringBuilder:append	(Ljava/lang/String;)Ljava/lang/StringBuilder;
    //   116: aload_3
    //   117: aload_3
    //   118: ldc 157
    //   120: invokeinterface 135 2 0
    //   125: invokeinterface 160 2 0
    //   130: invokevirtual 25	java/lang/StringBuilder:append	(Ljava/lang/String;)Ljava/lang/StringBuilder;
    //   133: invokevirtual 43	java/lang/StringBuilder:toString	()Ljava/lang/String;
    //   136: astore 4
    //   138: aload_3
    //   139: astore_1
    //   140: aload_3
    //   141: aload_3
    //   142: ldc 162
    //   144: invokeinterface 135 2 0
    //   149: invokeinterface 112 2 0
    //   154: istore_2
    //   155: aload_3
    //   156: astore_1
    //   157: new 18	java/lang/StringBuilder
    //   160: dup
    //   161: invokespecial 19	java/lang/StringBuilder:<init>	()V
    //   164: ldc 155
    //   166: invokevirtual 25	java/lang/StringBuilder:append	(Ljava/lang/String;)Ljava/lang/StringBuilder;
    //   169: aload_3
    //   170: aload_3
    //   171: ldc 164
    //   173: invokeinterface 135 2 0
    //   178: invokeinterface 160 2 0
    //   183: invokevirtual 25	java/lang/StringBuilder:append	(Ljava/lang/String;)Ljava/lang/StringBuilder;
    //   186: invokevirtual 43	java/lang/StringBuilder:toString	()Ljava/lang/String;
    //   189: astore 6
    //   191: aload_3
    //   192: astore_1
    //   193: aload_3
    //   194: aload_3
    //   195: ldc 125
    //   197: invokeinterface 135 2 0
    //   202: invokeinterface 153 2 0
    //   207: lstore 10
    //   209: aload_3
    //   210: astore_1
    //   211: new 166	kw
    //   214: dup
    //   215: invokespecial 167	kw:<init>	()V
    //   218: astore 7
    //   220: aload_3
    //   221: astore_1
    //   222: aload 7
    //   224: lload 8
    //   226: invokestatic 172	java/lang/Long:valueOf	(J)Ljava/lang/Long;
    //   229: invokevirtual 175	kw:a	(Ljava/lang/Long;)V
    //   232: aload_3
    //   233: astore_1
    //   234: aload 7
    //   236: aload 4
    //   238: invokevirtual 178	kw:a	(Ljava/lang/String;)V
    //   241: aload_3
    //   242: astore_1
    //   243: aload 7
    //   245: aload 6
    //   247: invokevirtual 180	kw:b	(Ljava/lang/String;)V
    //   250: aload_3
    //   251: astore_1
    //   252: aload 7
    //   254: iload_2
    //   255: invokevirtual 183	kw:a	(I)V
    //   258: aload_3
    //   259: astore_1
    //   260: aload 7
    //   262: lload 10
    //   264: invokevirtual 186	kw:a	(J)V
    //   267: aload_3
    //   268: astore_1
    //   269: aload 5
    //   271: aload 7
    //   273: invokeinterface 192 2 0
    //   278: pop
    //   279: goto -206 -> 73
    //   282: astore 4
    //   284: aload_3
    //   285: astore_1
    //   286: aload 4
    //   288: invokevirtual 118	java/lang/Exception:printStackTrace	()V
    //   291: aload_3
    //   292: ifnull +56 -> 348
    //   295: aload_3
    //   296: invokeinterface 115 1 0
    //   301: goto +47 -> 348
    //   304: aload_3
    //   305: ifnull +43 -> 348
    //   308: aload_3
    //   309: invokeinterface 115 1 0
    //   314: goto +34 -> 348
    //   317: astore_1
    //   318: aload_0
    //   319: monitorexit
    //   320: aload_1
    //   321: athrow
    //   322: astore_3
    //   323: aconst_null
    //   324: astore_1
    //   325: aload_1
    //   326: ifnull +9 -> 335
    //   329: aload_1
    //   330: invokeinterface 115 1 0
    //   335: aload_3
    //   336: athrow
    //   337: astore_3
    //   338: goto -13 -> 325
    //   341: astore 4
    //   343: aconst_null
    //   344: astore_3
    //   345: goto -61 -> 284
    //   348: goto -280 -> 68
    //
    // Exception table:
    //   from	to	target	type
    //   47	54	282	java/lang/Exception
    //   75	84	282	java/lang/Exception
    //   86	102	282	java/lang/Exception
    //   104	138	282	java/lang/Exception
    //   140	155	282	java/lang/Exception
    //   157	191	282	java/lang/Exception
    //   193	209	282	java/lang/Exception
    //   211	220	282	java/lang/Exception
    //   222	232	282	java/lang/Exception
    //   234	241	282	java/lang/Exception
    //   243	250	282	java/lang/Exception
    //   252	258	282	java/lang/Exception
    //   260	267	282	java/lang/Exception
    //   269	279	282	java/lang/Exception
    //   2	11	317	finally
    //   62	68	317	finally
    //   295	301	317	finally
    //   308	314	317	finally
    //   329	335	317	finally
    //   335	337	317	finally
    //   11	41	322	finally
    //   47	54	337	finally
    //   75	84	337	finally
    //   86	102	337	finally
    //   104	138	337	finally
    //   140	155	337	finally
    //   157	191	337	finally
    //   193	209	337	finally
    //   211	220	337	finally
    //   222	232	337	finally
    //   234	241	337	finally
    //   243	250	337	finally
    //   252	258	337	finally
    //   260	267	337	finally
    //   269	279	337	finally
    //   286	291	337	finally
    //   11	41	341	java/lang/Exception
  }

  public void a(Context paramContext)
  {
    try
    {
      ContentValues localContentValues = new ContentValues();
      localContentValues.put("sendState", Integer.valueOf(0));
      paramContext.getContentResolver().update(kd.a, localContentValues, "sendState=?", new String[] { String.valueOf(1) });
      return;
    }
    catch (Exception paramContext)
    {
      while (true)
        paramContext.printStackTrace();
    }
    finally
    {
    }
    throw paramContext;
  }

  void a(Context paramContext, long paramLong1, String paramString1, int paramInt, String paramString2, long paramLong2)
  {
    if (paramInt != 9);
    try
    {
      boolean bool = a(paramString1);
      if (!bool);
      while (true)
      {
        return;
        if (((paramInt <= 2) || (!b(paramContext, paramString1, paramLong1))) && ((paramInt != 9) || (!b(paramContext, paramString1, paramString2))))
        {
          ContentValues localContentValues = new ContentValues();
          localContentValues.put("date", Long.valueOf(paramLong1));
          localContentValues.put("eventId", paramString1);
          localContentValues.put("eventType", Integer.valueOf(paramInt));
          localContentValues.put("eventMessage", paramString2);
          localContentValues.put("count", Long.valueOf(paramLong2));
          paramContext.getContentResolver().insert(kd.a, localContentValues);
        }
      }
    }
    catch (Exception paramContext)
    {
      while (true)
        paramContext.printStackTrace();
    }
    finally
    {
    }
    throw paramContext;
  }

  void a(Context paramContext, String paramString, long paramLong)
  {
    while (true)
    {
      int i;
      try
      {
        boolean bool = a(paramString);
        if (!bool)
          return;
        i = c(paramContext, paramString, paramLong);
        if (i == 0)
        {
          a(paramContext, paramLong, paramString, 6, "", 1L);
          continue;
        }
      }
      catch (Exception paramContext)
      {
        paramContext.printStackTrace();
        continue;
      }
      finally
      {
      }
      a(paramContext, paramString, paramLong, i + 1);
    }
  }

  void a(Context paramContext, String paramString, long paramLong, int paramInt)
  {
    try
    {
      boolean bool = a(paramString);
      if (!bool);
      while (true)
      {
        return;
        try
        {
          ContentValues localContentValues = new ContentValues();
          localContentValues.put("count", Integer.valueOf(paramInt));
          paramContext.getContentResolver().update(kd.a, localContentValues, "eventId=? AND date=?", new String[] { paramString, String.valueOf(paramLong) });
        }
        catch (Exception paramContext)
        {
          paramContext.printStackTrace();
        }
      }
    }
    finally
    {
    }
    throw paramContext;
  }

  public void a(Context paramContext, String paramString1, String paramString2)
  {
    try
    {
      ContentValues localContentValues;
      if (c(paramContext, paramString1) != null)
      {
        localContentValues = new ContentValues();
        localContentValues.put("key", paramString1);
        localContentValues.put("value", paramString2);
        localContentValues.put("type", "string");
        paramContext.getContentResolver().update(kf.a, localContentValues, "key=?", new String[] { paramString1 });
      }
      while (true)
      {
        return;
        localContentValues = new ContentValues();
        localContentValues.put("key", paramString1);
        localContentValues.put("value", paramString2);
        localContentValues.put("type", "string");
        paramContext.getContentResolver().insert(kf.a, localContentValues);
      }
    }
    catch (Exception paramContext)
    {
      while (true)
        paramContext.printStackTrace();
    }
    finally
    {
    }
    throw paramContext;
  }

  void a(Context paramContext, kw paramkw, int paramInt)
  {
    try
    {
      ContentValues localContentValues = new ContentValues();
      localContentValues.put("sendState", Integer.valueOf(paramInt));
      paramContext.getContentResolver().update(kd.a, localContentValues, "eventId=? AND date=? AND eventMessage=? AND eventType=?", new String[] { paramkw.b(), String.valueOf(paramkw.a()), paramkw.d(), String.valueOf(paramkw.c()) });
      return;
    }
    catch (Exception paramContext)
    {
      while (true)
        paramContext.printStackTrace();
    }
    finally
    {
    }
    throw paramContext;
  }

  boolean a(Context paramContext, String paramString)
  {
    boolean bool = true;
    try
    {
      if (kn.a)
        kx.a("DF_SQL", "deleteByEventId:" + paramString);
      paramContext.getContentResolver().delete(kd.a, "eventId=?", new String[] { paramString });
      return bool;
    }
    catch (Exception paramContext)
    {
      while (true)
      {
        paramContext.printStackTrace();
        bool = false;
      }
    }
    finally
    {
    }
    throw paramContext;
  }

  void b(Context paramContext)
  {
    try
    {
      ContentValues localContentValues = new ContentValues();
      localContentValues.put("sendState", Integer.valueOf(2));
      paramContext.getContentResolver().update(kd.a, localContentValues, "sendState=?", new String[] { String.valueOf(1) });
      return;
    }
    catch (Exception paramContext)
    {
      while (true)
        paramContext.printStackTrace();
    }
    finally
    {
    }
    throw paramContext;
  }

  boolean b(Context paramContext, String paramString)
  {
    boolean bool = true;
    try
    {
      if (kn.a)
        kx.a("DF_SQL", "deleOtherErr:" + paramString);
      paramContext.getContentResolver().delete(kd.a, "eventMessage<>? AND eventType=?", new String[] { paramString, String.valueOf(9) });
      return bool;
    }
    catch (Exception paramContext)
    {
      while (true)
      {
        paramContext.printStackTrace();
        bool = false;
      }
    }
    finally
    {
    }
    throw paramContext;
  }

  // ERROR //
  String c(Context paramContext, String paramString)
  {
    // Byte code:
    //   0: aconst_null
    //   1: astore_3
    //   2: aload_0
    //   3: monitorenter
    //   4: aload_1
    //   5: invokevirtual 54	android/content/Context:getContentResolver	()Landroid/content/ContentResolver;
    //   8: astore_1
    //   9: getstatic 256	kf:a	Landroid/net/Uri;
    //   12: astore 4
    //   14: aload_2
    //   15: invokestatic 269	java/lang/String:valueOf	(Ljava/lang/Object;)Ljava/lang/String;
    //   18: astore_2
    //   19: aload_1
    //   20: aload 4
    //   22: iconst_1
    //   23: anewarray 74	java/lang/String
    //   26: dup
    //   27: iconst_0
    //   28: ldc 249
    //   30: aastore
    //   31: ldc_w 258
    //   34: iconst_1
    //   35: anewarray 74	java/lang/String
    //   38: dup
    //   39: iconst_0
    //   40: aload_2
    //   41: aastore
    //   42: aconst_null
    //   43: invokevirtual 102	android/content/ContentResolver:query	(Landroid/net/Uri;[Ljava/lang/String;Ljava/lang/String;[Ljava/lang/String;Ljava/lang/String;)Landroid/database/Cursor;
    //   46: astore_1
    //   47: aload_1
    //   48: ifnull +18 -> 66
    //   51: aload_1
    //   52: astore_2
    //   53: aload_1
    //   54: invokeinterface 128 1 0
    //   59: istore 5
    //   61: iload 5
    //   63: ifne +19 -> 82
    //   66: aload_1
    //   67: ifnull +9 -> 76
    //   70: aload_1
    //   71: invokeinterface 115 1 0
    //   76: aconst_null
    //   77: astore_2
    //   78: aload_0
    //   79: monitorexit
    //   80: aload_2
    //   81: areturn
    //   82: aload_1
    //   83: astore_2
    //   84: aload_1
    //   85: invokeinterface 131 1 0
    //   90: ifeq +42 -> 132
    //   93: aload_1
    //   94: astore_2
    //   95: aload_1
    //   96: aload_1
    //   97: ldc 249
    //   99: invokeinterface 135 2 0
    //   104: invokeinterface 160 2 0
    //   109: astore_3
    //   110: aload_3
    //   111: astore_2
    //   112: aload_1
    //   113: ifnull -35 -> 78
    //   116: aload_1
    //   117: invokeinterface 115 1 0
    //   122: aload_3
    //   123: astore_2
    //   124: goto -46 -> 78
    //   127: astore_1
    //   128: aload_0
    //   129: monitorexit
    //   130: aload_1
    //   131: athrow
    //   132: aload_1
    //   133: ifnull +9 -> 142
    //   136: aload_1
    //   137: invokeinterface 115 1 0
    //   142: aconst_null
    //   143: astore_2
    //   144: goto -66 -> 78
    //   147: astore_3
    //   148: aconst_null
    //   149: astore_1
    //   150: aload_1
    //   151: astore_2
    //   152: aload_3
    //   153: invokevirtual 118	java/lang/Exception:printStackTrace	()V
    //   156: aload_1
    //   157: ifnull -15 -> 142
    //   160: aload_1
    //   161: invokeinterface 115 1 0
    //   166: goto -24 -> 142
    //   169: aload_2
    //   170: ifnull +9 -> 179
    //   173: aload_2
    //   174: invokeinterface 115 1 0
    //   179: aload_1
    //   180: athrow
    //   181: astore_1
    //   182: goto -13 -> 169
    //   185: astore_3
    //   186: goto -36 -> 150
    //   189: astore_1
    //   190: aload_3
    //   191: astore_2
    //   192: goto -23 -> 169
    //
    // Exception table:
    //   from	to	target	type
    //   70	76	127	finally
    //   116	122	127	finally
    //   136	142	127	finally
    //   160	166	127	finally
    //   173	179	127	finally
    //   179	181	127	finally
    //   4	47	147	java/lang/Exception
    //   53	61	181	finally
    //   84	93	181	finally
    //   95	110	181	finally
    //   152	156	181	finally
    //   53	61	185	java/lang/Exception
    //   84	93	185	java/lang/Exception
    //   95	110	185	java/lang/Exception
    //   4	47	189	finally
  }

  List<kw> c(Context paramContext)
  {
    try
    {
      paramContext = a(paramContext, 6);
      return paramContext;
    }
    finally
    {
      paramContext = finally;
    }
    throw paramContext;
  }

  boolean d(Context paramContext)
  {
    boolean bool = true;
    try
    {
      if (kn.a)
        kx.a("DF_SQL", "deleteBySuccess.......");
      paramContext.getContentResolver().delete(kd.a, "sendState=?", new String[] { String.valueOf(2) });
      return bool;
    }
    catch (Exception paramContext)
    {
      while (true)
      {
        paramContext.printStackTrace();
        bool = false;
      }
    }
    finally
    {
    }
    throw paramContext;
  }

  // ERROR //
  int e(Context paramContext)
  {
    // Byte code:
    //   0: aload_1
    //   1: invokevirtual 54	android/content/Context:getContentResolver	()Landroid/content/ContentResolver;
    //   4: getstatic 59	kd:a	Landroid/net/Uri;
    //   7: iconst_1
    //   8: anewarray 74	java/lang/String
    //   11: dup
    //   12: iconst_0
    //   13: ldc 92
    //   15: aastore
    //   16: aconst_null
    //   17: aconst_null
    //   18: aconst_null
    //   19: invokevirtual 102	android/content/ContentResolver:query	(Landroid/net/Uri;[Ljava/lang/String;Ljava/lang/String;[Ljava/lang/String;Ljava/lang/String;)Landroid/database/Cursor;
    //   22: astore_1
    //   23: aload_1
    //   24: ifnull +83 -> 107
    //   27: aload_1
    //   28: astore_2
    //   29: aload_1
    //   30: invokeinterface 108 1 0
    //   35: ifeq +72 -> 107
    //   38: aload_1
    //   39: astore_2
    //   40: aload_1
    //   41: iconst_0
    //   42: invokeinterface 112 2 0
    //   47: istore 4
    //   49: aload_1
    //   50: astore_2
    //   51: getstatic 32	kn:a	Z
    //   54: ifeq +32 -> 86
    //   57: aload_1
    //   58: astore_2
    //   59: ldc 34
    //   61: new 18	java/lang/StringBuilder
    //   64: dup
    //   65: invokespecial 19	java/lang/StringBuilder:<init>	()V
    //   68: ldc_w 293
    //   71: invokevirtual 25	java/lang/StringBuilder:append	(Ljava/lang/String;)Ljava/lang/StringBuilder;
    //   74: iload 4
    //   76: invokevirtual 296	java/lang/StringBuilder:append	(I)Ljava/lang/StringBuilder;
    //   79: invokevirtual 43	java/lang/StringBuilder:toString	()Ljava/lang/String;
    //   82: invokestatic 302	android/util/Log:v	(Ljava/lang/String;Ljava/lang/String;)I
    //   85: pop
    //   86: iload 4
    //   88: istore 5
    //   90: aload_1
    //   91: ifnull +13 -> 104
    //   94: aload_1
    //   95: invokeinterface 115 1 0
    //   100: iload 4
    //   102: istore 5
    //   104: iload 5
    //   106: ireturn
    //   107: aload_1
    //   108: ifnull +103 -> 211
    //   111: aload_1
    //   112: invokeinterface 115 1 0
    //   117: iconst_0
    //   118: ireturn
    //   119: astore_3
    //   120: aconst_null
    //   121: astore_1
    //   122: iconst_0
    //   123: istore 4
    //   125: aload_1
    //   126: astore_2
    //   127: getstatic 32	kn:a	Z
    //   130: ifeq +34 -> 164
    //   133: aload_1
    //   134: astore_2
    //   135: ldc 34
    //   137: new 18	java/lang/StringBuilder
    //   140: dup
    //   141: invokespecial 19	java/lang/StringBuilder:<init>	()V
    //   144: ldc_w 304
    //   147: invokevirtual 25	java/lang/StringBuilder:append	(Ljava/lang/String;)Ljava/lang/StringBuilder;
    //   150: aload_3
    //   151: invokevirtual 307	java/lang/Exception:getMessage	()Ljava/lang/String;
    //   154: invokevirtual 25	java/lang/StringBuilder:append	(Ljava/lang/String;)Ljava/lang/StringBuilder;
    //   157: invokevirtual 43	java/lang/StringBuilder:toString	()Ljava/lang/String;
    //   160: invokestatic 310	android/util/Log:w	(Ljava/lang/String;Ljava/lang/String;)I
    //   163: pop
    //   164: iload 4
    //   166: istore 5
    //   168: aload_1
    //   169: ifnull -65 -> 104
    //   172: aload_1
    //   173: invokeinterface 115 1 0
    //   178: iload 4
    //   180: ireturn
    //   181: astore_1
    //   182: aconst_null
    //   183: astore_2
    //   184: aload_2
    //   185: ifnull +9 -> 194
    //   188: aload_2
    //   189: invokeinterface 115 1 0
    //   194: aload_1
    //   195: athrow
    //   196: astore_1
    //   197: goto -13 -> 184
    //   200: astore_3
    //   201: iconst_0
    //   202: istore 4
    //   204: goto -79 -> 125
    //   207: astore_3
    //   208: goto -83 -> 125
    //   211: iconst_0
    //   212: ireturn
    //
    // Exception table:
    //   from	to	target	type
    //   0	23	119	java/lang/Exception
    //   0	23	181	finally
    //   29	38	196	finally
    //   40	49	196	finally
    //   51	57	196	finally
    //   59	86	196	finally
    //   127	133	196	finally
    //   135	164	196	finally
    //   29	38	200	java/lang/Exception
    //   40	49	200	java/lang/Exception
    //   51	57	207	java/lang/Exception
    //   59	86	207	java/lang/Exception
  }

  // ERROR //
  boolean f(Context paramContext)
  {
    // Byte code:
    //   0: iconst_0
    //   1: istore 7
    //   3: aload_0
    //   4: monitorenter
    //   5: new 141	java/util/ArrayList
    //   8: dup
    //   9: invokespecial 142	java/util/ArrayList:<init>	()V
    //   12: astore 4
    //   14: aload_1
    //   15: invokevirtual 54	android/content/Context:getContentResolver	()Landroid/content/ContentResolver;
    //   18: getstatic 59	kd:a	Landroid/net/Uri;
    //   21: aconst_null
    //   22: ldc_w 313
    //   25: iconst_3
    //   26: anewarray 74	java/lang/String
    //   29: dup
    //   30: iconst_0
    //   31: iconst_3
    //   32: invokestatic 147	java/lang/String:valueOf	(I)Ljava/lang/String;
    //   35: aastore
    //   36: dup
    //   37: iconst_1
    //   38: iconst_4
    //   39: invokestatic 147	java/lang/String:valueOf	(I)Ljava/lang/String;
    //   42: aastore
    //   43: dup
    //   44: iconst_2
    //   45: iconst_5
    //   46: invokestatic 147	java/lang/String:valueOf	(I)Ljava/lang/String;
    //   49: aastore
    //   50: aconst_null
    //   51: invokevirtual 102	android/content/ContentResolver:query	(Landroid/net/Uri;[Ljava/lang/String;Ljava/lang/String;[Ljava/lang/String;Ljava/lang/String;)Landroid/database/Cursor;
    //   54: astore_3
    //   55: aload_3
    //   56: ifnull +18 -> 74
    //   59: aload_3
    //   60: astore_2
    //   61: aload_3
    //   62: invokeinterface 128 1 0
    //   67: istore 5
    //   69: iload 5
    //   71: ifne +26 -> 97
    //   74: iload 7
    //   76: istore 6
    //   78: aload_3
    //   79: ifnull +13 -> 92
    //   82: aload_3
    //   83: invokeinterface 115 1 0
    //   88: iload 7
    //   90: istore 6
    //   92: aload_0
    //   93: monitorexit
    //   94: iload 6
    //   96: ireturn
    //   97: aload_3
    //   98: astore_2
    //   99: aload_3
    //   100: invokeinterface 131 1 0
    //   105: ifeq +133 -> 238
    //   108: aload_3
    //   109: astore_2
    //   110: aload 4
    //   112: aload_3
    //   113: aload_3
    //   114: ldc_w 315
    //   117: invokeinterface 135 2 0
    //   122: invokeinterface 112 2 0
    //   127: invokestatic 147	java/lang/String:valueOf	(I)Ljava/lang/String;
    //   130: invokeinterface 192 2 0
    //   135: pop
    //   136: aload_3
    //   137: astore_2
    //   138: aload 4
    //   140: invokeinterface 318 1 0
    //   145: ifle -48 -> 97
    //   148: aload_3
    //   149: astore_2
    //   150: aload 4
    //   152: invokeinterface 318 1 0
    //   157: sipush 500
    //   160: irem
    //   161: ifne -64 -> 97
    //   164: aload_3
    //   165: astore_2
    //   166: aload_0
    //   167: aload_1
    //   168: aload 4
    //   170: aload 4
    //   172: invokeinterface 318 1 0
    //   177: anewarray 74	java/lang/String
    //   180: invokeinterface 322 2 0
    //   185: checkcast 324	[Ljava/lang/String;
    //   188: invokespecial 326	kl:a	(Landroid/content/Context;[Ljava/lang/String;)V
    //   191: aload_3
    //   192: astore_2
    //   193: aload 4
    //   195: invokeinterface 329 1 0
    //   200: goto -103 -> 97
    //   203: astore_1
    //   204: aload_3
    //   205: astore_2
    //   206: aload_1
    //   207: invokevirtual 118	java/lang/Exception:printStackTrace	()V
    //   210: aload_3
    //   211: astore_2
    //   212: ldc 34
    //   214: aload_1
    //   215: invokevirtual 330	java/lang/Exception:toString	()Ljava/lang/String;
    //   218: invokestatic 332	android/util/Log:e	(Ljava/lang/String;Ljava/lang/String;)I
    //   221: pop
    //   222: aload_3
    //   223: ifnull +106 -> 329
    //   226: aload_3
    //   227: invokeinterface 115 1 0
    //   232: iconst_0
    //   233: istore 6
    //   235: goto -143 -> 92
    //   238: aload_3
    //   239: astore_2
    //   240: aload 4
    //   242: invokeinterface 335 1 0
    //   247: ifne +39 -> 286
    //   250: aload_3
    //   251: astore_2
    //   252: aload_0
    //   253: aload_1
    //   254: aload 4
    //   256: aload 4
    //   258: invokeinterface 318 1 0
    //   263: anewarray 74	java/lang/String
    //   266: invokeinterface 322 2 0
    //   271: checkcast 324	[Ljava/lang/String;
    //   274: invokespecial 326	kl:a	(Landroid/content/Context;[Ljava/lang/String;)V
    //   277: aload_3
    //   278: astore_2
    //   279: aload 4
    //   281: invokeinterface 329 1 0
    //   286: aload_3
    //   287: ifnull +48 -> 335
    //   290: aload_3
    //   291: invokeinterface 115 1 0
    //   296: iconst_1
    //   297: istore 6
    //   299: goto -64 -> 235
    //   302: aload_2
    //   303: ifnull +9 -> 312
    //   306: aload_2
    //   307: invokeinterface 115 1 0
    //   312: aload_1
    //   313: athrow
    //   314: astore_1
    //   315: aload_0
    //   316: monitorexit
    //   317: aload_1
    //   318: athrow
    //   319: astore_1
    //   320: goto -18 -> 302
    //   323: astore_1
    //   324: aconst_null
    //   325: astore_3
    //   326: goto -122 -> 204
    //   329: iconst_0
    //   330: istore 6
    //   332: goto -97 -> 235
    //   335: iconst_1
    //   336: istore 6
    //   338: goto -103 -> 235
    //   341: astore_1
    //   342: aconst_null
    //   343: astore_2
    //   344: goto -42 -> 302
    //
    // Exception table:
    //   from	to	target	type
    //   61	69	203	java/lang/Exception
    //   99	108	203	java/lang/Exception
    //   110	136	203	java/lang/Exception
    //   138	148	203	java/lang/Exception
    //   150	164	203	java/lang/Exception
    //   166	191	203	java/lang/Exception
    //   193	200	203	java/lang/Exception
    //   240	250	203	java/lang/Exception
    //   252	277	203	java/lang/Exception
    //   279	286	203	java/lang/Exception
    //   5	14	314	finally
    //   82	88	314	finally
    //   226	232	314	finally
    //   290	296	314	finally
    //   306	312	314	finally
    //   312	314	314	finally
    //   61	69	319	finally
    //   99	108	319	finally
    //   110	136	319	finally
    //   138	148	319	finally
    //   150	164	319	finally
    //   166	191	319	finally
    //   193	200	319	finally
    //   206	210	319	finally
    //   212	222	319	finally
    //   240	250	319	finally
    //   252	277	319	finally
    //   279	286	319	finally
    //   14	55	323	java/lang/Exception
    //   14	55	341	finally
  }
}

/* Location:           classes-dex2jar.jar
 * Qualified Name:     kl
 * JD-Core Version:    0.6.2
 */