package cmcm.com.myapplication;

import android.content.ContentResolver;
import android.content.ContentValues;
import android.content.Context;
import android.os.Handler;
import android.os.Handler.Callback;
import android.os.HandlerThread;
import android.text.TextUtils;
import android.util.Base64;
import com.duapps.ad.stats.DuAdCacheProvider;
import java.io.IOException;
import java.io.InputStreamReader;
import java.io.Reader;
import java.net.URI;
import java.security.MessageDigest;
import java.security.NoSuchAlgorithmException;
import java.util.List;
import java.util.zip.GZIPInputStream;
import org.apache.http.Header;
import org.apache.http.HttpEntity;
import org.apache.http.HttpResponse;
import org.apache.http.StatusLine;
import org.apache.http.client.utils.URLEncodedUtils;
import org.apache.http.message.BasicNameValuePair;
import org.apache.http.util.CharArrayBuffer;
import org.json.JSONException;
import org.json.JSONObject;

public final class ob
  implements Callback
{
  private static ob b;
  private static String c = "http://api.mobula.sdk.duapps.com/adunion/slot/getSrcPrio?";
  private static String d = "http://rts.mobula.sdk.duapps.com/orts/rp?";
  private static String e = "http://rts.mobula.sdk.duapps.com/orts/rpb?";
  private int a = 0;
  private Context f;
  private Handler g;

  private ob(Context paramContext)
  {
    this.f = paramContext;
    paramContext = new HandlerThread("stts", 10);
    paramContext.start();
    this.g = new Handler(paramContext.getLooper(), this);
    this.g.sendEmptyMessage(4);
    long l2 = na.d(this.f);
    long l3 = System.currentTimeMillis();
    long l4 = l3 - l2;
    if (l4 < 0L)
    {
      na.c(this.f);
      return;
    }
    if (l4 <= 21600000L)
      l1 = l3 + 21600000L - l2;
    this.g.sendEmptyMessageDelayed(5, l1);
  }

  public static void a(Context paramContext)
  {
    try
    {
      if (b == null)
        b = new ob(paramContext.getApplicationContext());
      return;
    }
    finally
    {
      paramContext = finally;
    }
    throw paramContext;
  }

  private static void a(HttpResponse paramHttpResponse)
  {
    Object localObject = paramHttpResponse.getEntity();
    paramHttpResponse = ((HttpEntity)localObject).getContent();
    localObject = ((HttpEntity)localObject).getContentEncoding();
    if ((localObject != null) && (((Header)localObject).getValue().indexOf("gzip") != -1))
      paramHttpResponse = new GZIPInputStream(paramHttpResponse);
    while (true)
    {
      localObject = new InputStreamReader(paramHttpResponse, "UTF-8");
      CharArrayBuffer localCharArrayBuffer = new CharArrayBuffer(1024);
      char[] arrayOfChar = new char[1024];
      while (true)
      {
        int i = ((Reader)localObject).read(arrayOfChar);
        if (i == -1)
          break;
        localCharArrayBuffer.append(arrayOfChar, 0, i);
      }
      np.a(paramHttpResponse);
      paramHttpResponse = localCharArrayBuffer.toString();
      mv.c("ToolStatsCore", "result = " + paramHttpResponse);
      try
      {
        paramHttpResponse = new JSONObject(paramHttpResponse).getJSONObject("responseHeader");
        if (paramHttpResponse.getInt("status") != 200)
          throw new IOException(paramHttpResponse.getString("msg"));
      }
      catch (JSONException paramHttpResponse)
      {
      }
      return;
    }
  }

  private boolean a(String paramString1, String paramString2, String paramString3, long paramLong)
  {
    Object localObject3 = null;
    Object localObject2 = null;
    Object localObject1 = mu.a(this.f, paramString1);
    String str = String.valueOf(System.currentTimeMillis());
    ((List)localObject1).add(new BasicNameValuePair("mdu", "adsdk"));
    ((List)localObject1).add(new BasicNameValuePair("rv", "1.0"));
    ((List)localObject1).add(new BasicNameValuePair("ts", str));
    ((List)localObject1).add(new BasicNameValuePair("seq", Long.toString(paramLong)));
    ((List)localObject1).add(new BasicNameValuePair("stype", paramString2));
    try
    {
      MessageDigest localMessageDigest = MessageDigest.getInstance("MD5");
      localMessageDigest.update(paramString3.getBytes());
      localMessageDigest.update(str.getBytes());
      localMessageDigest.update(paramString1.getBytes());
      ((List)localObject1).add(new BasicNameValuePair("s", np.a(localMessageDigest.digest())));
      str = URLEncodedUtils.format((List)localObject1, "UTF-8");
      localObject1 = localObject2;
      paramString1 = localObject3;
      try
      {
        if (paramString2.equalsIgnoreCase("behavior"))
        {
          localObject1 = localObject2;
          paramString1 = localObject3;
        }
        for (paramString2 = new URI(e + str); ; paramString2 = new URI(d + str))
        {
          localObject1 = localObject2;
          paramString1 = localObject3;
          paramString2 = mj.a(paramString2, paramString3, null);
          localObject1 = paramString2;
          paramString1 = paramString2;
          int i = paramString2.getStatusLine().getStatusCode();
          localObject1 = paramString2;
          paramString1 = paramString2;
          mv.c("ToolStatsCore", "status code = " + i);
          if (i != 200)
            break;
          localObject1 = paramString2;
          paramString1 = paramString2;
          if (mv.a())
          {
            localObject1 = paramString2;
            paramString1 = paramString2;
            a(paramString2);
          }
          return true;
          localObject1 = localObject2;
          paramString1 = localObject3;
        }
      }
      catch (Exception paramString2)
      {
        paramString1 = (String)localObject1;
        mv.a("ToolStatsCore", "post failed.", paramString2);
        mj.a((HttpResponse)localObject1);
        return false;
        return false;
      }
      finally
      {
        mj.a(paramString1);
      }
    }
    catch (NoSuchAlgorithmException paramString1)
    {
    }
    return false;
  }

  public static ob b(Context paramContext)
  {
    a(paramContext);
    return b;
  }

  final void a(String paramString1, String paramString2, int paramInt)
  {
    Object localObject = this.f;
    localObject = nm.a();
    if ((TextUtils.isEmpty((CharSequence)localObject)) || (TextUtils.isEmpty(paramString2)))
      if (mv.a())
        mv.c("ToolStatsCore", "Discard ls=" + (String)localObject + ";rp=" + paramString2);
    while (true)
    {
      return;
      if (mv.a())
        mv.c("ToolStatsCore", "rept = " + paramString2);
      ContentValues localContentValues = new ContentValues(3);
      localContentValues.put("ts", Long.valueOf(System.currentTimeMillis()));
      localContentValues.put("content", Base64.encode(paramString2.getBytes(), 3));
      localContentValues.put("ls", (String)localObject);
      localContentValues.put("stype", paramString1);
      try
      {
        this.f.getContentResolver().insert(DuAdCacheProvider.a(this.f, 4), localContentValues);
        if (paramInt != 0)
          continue;
        this.g.sendEmptyMessageDelayed(3, 5000L);
        return;
      }
      catch (Exception paramString1)
      {
        while (true)
          mv.a("ToolStatsCore", "mDatabase reportEvent() exception: ", paramString1);
      }
    }
  }

  // ERROR //
  public final boolean handleMessage(android.os.Message paramMessage)
  {
    // Byte code:
    //   0: aload_1
    //   1: getfield 389	android/os/Message:what	I
    //   4: tableswitch	default:+28 -> 32, 3:+30->34, 4:+805->809, 5:+836->840
    //   33: ireturn
    //   34: aload_0
    //   35: getfield 62	ob:g	Landroid/os/Handler;
    //   38: iconst_3
    //   39: invokevirtual 392	android/os/Handler:removeMessages	(I)V
    //   42: invokestatic 77	java/lang/System:currentTimeMillis	()J
    //   45: lstore 16
    //   47: new 394	org/json/JSONStringer
    //   50: dup
    //   51: invokespecial 395	org/json/JSONStringer:<init>	()V
    //   54: astore 12
    //   56: new 168	java/lang/StringBuilder
    //   59: dup
    //   60: invokespecial 286	java/lang/StringBuilder:<init>	()V
    //   63: astore 11
    //   65: lload 16
    //   67: ldc2_w 396
    //   70: lsub
    //   71: lstore 16
    //   73: aload_0
    //   74: getfield 41	ob:f	Landroid/content/Context;
    //   77: invokevirtual 367	android/content/Context:getContentResolver	()Landroid/content/ContentResolver;
    //   80: aload_0
    //   81: getfield 41	ob:f	Landroid/content/Context;
    //   84: iconst_4
    //   85: invokestatic 372	com/duapps/ad/stats/DuAdCacheProvider:a	(Landroid/content/Context;I)Landroid/net/Uri;
    //   88: iconst_5
    //   89: anewarray 125	java/lang/String
    //   92: dup
    //   93: iconst_0
    //   94: ldc 239
    //   96: aastore
    //   97: dup
    //   98: iconst_1
    //   99: ldc_w 350
    //   102: aastore
    //   103: dup
    //   104: iconst_2
    //   105: ldc_w 361
    //   108: aastore
    //   109: dup
    //   110: iconst_3
    //   111: ldc 247
    //   113: aastore
    //   114: dup
    //   115: iconst_4
    //   116: ldc_w 399
    //   119: aastore
    //   120: ldc_w 401
    //   123: iconst_1
    //   124: anewarray 125	java/lang/String
    //   127: dup
    //   128: iconst_0
    //   129: lload 16
    //   131: invokestatic 219	java/lang/String:valueOf	(J)Ljava/lang/String;
    //   134: aastore
    //   135: ldc_w 403
    //   138: invokevirtual 407	android/content/ContentResolver:query	(Landroid/net/Uri;[Ljava/lang/String;Ljava/lang/String;[Ljava/lang/String;Ljava/lang/String;)Landroid/database/Cursor;
    //   141: astore_3
    //   142: aload_3
    //   143: ifnonnull +51 -> 194
    //   146: aload_3
    //   147: ifnull +18 -> 165
    //   150: aload_3
    //   151: invokeinterface 412 1 0
    //   156: ifne +9 -> 165
    //   159: aload_3
    //   160: invokeinterface 415 1 0
    //   165: aload_0
    //   166: aload_0
    //   167: getfield 39	ob:a	I
    //   170: iconst_1
    //   171: iadd
    //   172: putfield 39	ob:a	I
    //   175: iconst_3
    //   176: aload_0
    //   177: getfield 39	ob:a	I
    //   180: if_icmple +621 -> 801
    //   183: aload_0
    //   184: getfield 62	ob:g	Landroid/os/Handler;
    //   187: iconst_3
    //   188: invokevirtual 66	android/os/Handler:sendEmptyMessage	(I)Z
    //   191: pop
    //   192: iconst_1
    //   193: ireturn
    //   194: aload_3
    //   195: astore 4
    //   197: aload_3
    //   198: invokeinterface 418 1 0
    //   203: ifgt +34 -> 237
    //   206: aload_3
    //   207: astore 4
    //   209: aload_3
    //   210: invokeinterface 415 1 0
    //   215: aload_3
    //   216: ifnull -51 -> 165
    //   219: aload_3
    //   220: invokeinterface 412 1 0
    //   225: ifne -60 -> 165
    //   228: aload_3
    //   229: invokeinterface 415 1 0
    //   234: goto -69 -> 165
    //   237: aload_3
    //   238: astore 4
    //   240: aload 12
    //   242: invokevirtual 422	org/json/JSONStringer:array	()Lorg/json/JSONStringer;
    //   245: pop
    //   246: aconst_null
    //   247: astore_2
    //   248: aconst_null
    //   249: astore_1
    //   250: iconst_0
    //   251: istore 14
    //   253: aload_3
    //   254: astore 4
    //   256: aload_2
    //   257: astore 6
    //   259: aload_1
    //   260: astore 5
    //   262: aload_3
    //   263: invokeinterface 425 1 0
    //   268: ifeq +217 -> 485
    //   271: aload_3
    //   272: astore 4
    //   274: aload_2
    //   275: astore 6
    //   277: aload_1
    //   278: astore 5
    //   280: aload_3
    //   281: iconst_0
    //   282: invokeinterface 429 2 0
    //   287: lstore 18
    //   289: aload_3
    //   290: astore 4
    //   292: aload_2
    //   293: astore 6
    //   295: aload_1
    //   296: astore 5
    //   298: aload_3
    //   299: iconst_1
    //   300: invokeinterface 433 2 0
    //   305: astore 13
    //   307: aload_3
    //   308: astore 4
    //   310: aload_2
    //   311: astore 6
    //   313: aload_1
    //   314: astore 5
    //   316: aload_3
    //   317: iconst_2
    //   318: invokeinterface 436 2 0
    //   323: astore 9
    //   325: aload_3
    //   326: astore 4
    //   328: aload_2
    //   329: astore 6
    //   331: aload_1
    //   332: astore 5
    //   334: aload_3
    //   335: iconst_3
    //   336: invokeinterface 436 2 0
    //   341: astore 10
    //   343: aload_1
    //   344: astore 7
    //   346: aload_1
    //   347: ifnonnull +578 -> 925
    //   350: aload 9
    //   352: astore 7
    //   354: goto +571 -> 925
    //   357: aload 8
    //   359: astore_2
    //   360: aload 7
    //   362: astore_1
    //   363: aload_3
    //   364: astore 4
    //   366: aload 8
    //   368: astore 6
    //   370: aload 7
    //   372: astore 5
    //   374: aload 7
    //   376: aload 9
    //   378: invokevirtual 439	java/lang/String:equals	(Ljava/lang/Object;)Z
    //   381: ifeq -128 -> 253
    //   384: aload 8
    //   386: astore_2
    //   387: aload 7
    //   389: astore_1
    //   390: aload_3
    //   391: astore 4
    //   393: aload 8
    //   395: astore 6
    //   397: aload 7
    //   399: astore 5
    //   401: aload 8
    //   403: aload 10
    //   405: invokevirtual 439	java/lang/String:equals	(Ljava/lang/Object;)Z
    //   408: ifeq -155 -> 253
    //   411: aload_3
    //   412: astore 4
    //   414: aload 8
    //   416: astore 6
    //   418: aload 7
    //   420: astore 5
    //   422: aload 12
    //   424: new 184	org/json/JSONObject
    //   427: dup
    //   428: new 125	java/lang/String
    //   431: dup
    //   432: aload 13
    //   434: iconst_3
    //   435: invokestatic 442	android/util/Base64:decode	([BI)[B
    //   438: invokespecial 444	java/lang/String:<init>	([B)V
    //   441: invokespecial 185	org/json/JSONObject:<init>	(Ljava/lang/String;)V
    //   444: invokevirtual 448	org/json/JSONStringer:value	(Ljava/lang/Object;)Lorg/json/JSONStringer;
    //   447: pop
    //   448: aload_3
    //   449: astore 4
    //   451: aload 8
    //   453: astore 6
    //   455: aload 7
    //   457: astore 5
    //   459: aload 11
    //   461: lload 18
    //   463: invokevirtual 451	java/lang/StringBuilder:append	(J)Ljava/lang/StringBuilder;
    //   466: ldc_w 453
    //   469: invokevirtual 176	java/lang/StringBuilder:append	(Ljava/lang/String;)Ljava/lang/StringBuilder;
    //   472: pop
    //   473: iconst_1
    //   474: istore 14
    //   476: aload 8
    //   478: astore_2
    //   479: aload 7
    //   481: astore_1
    //   482: goto -229 -> 253
    //   485: aload_3
    //   486: astore 4
    //   488: aload_2
    //   489: astore 6
    //   491: aload_1
    //   492: astore 5
    //   494: aload 12
    //   496: invokevirtual 456	org/json/JSONStringer:endArray	()Lorg/json/JSONStringer;
    //   499: pop
    //   500: aload_3
    //   501: ifnull +418 -> 919
    //   504: aload_3
    //   505: invokeinterface 412 1 0
    //   510: ifne +409 -> 919
    //   513: aload_3
    //   514: invokeinterface 415 1 0
    //   519: iconst_0
    //   520: istore 15
    //   522: iload 14
    //   524: ifeq -359 -> 165
    //   527: iload 15
    //   529: ifne -364 -> 165
    //   532: aload_1
    //   533: ifnull -368 -> 165
    //   536: aload_2
    //   537: ifnull -372 -> 165
    //   540: aload 11
    //   542: aload 11
    //   544: invokevirtual 459	java/lang/StringBuilder:length	()I
    //   547: iconst_1
    //   548: isub
    //   549: invokevirtual 462	java/lang/StringBuilder:deleteCharAt	(I)Ljava/lang/StringBuilder;
    //   552: pop
    //   553: aload 12
    //   555: invokevirtual 463	org/json/JSONStringer:toString	()Ljava/lang/String;
    //   558: astore_3
    //   559: aload_0
    //   560: getfield 41	ob:f	Landroid/content/Context;
    //   563: ldc 241
    //   565: invokestatic 466	na:a	(Landroid/content/Context;Ljava/lang/String;)J
    //   568: lstore 18
    //   570: aload_0
    //   571: aload_1
    //   572: aload_2
    //   573: aload_3
    //   574: lload 18
    //   576: invokespecial 468	ob:a	(Ljava/lang/String;Ljava/lang/String;Ljava/lang/String;J)Z
    //   579: ifeq -414 -> 165
    //   582: aload_0
    //   583: getfield 41	ob:f	Landroid/content/Context;
    //   586: invokevirtual 367	android/content/Context:getContentResolver	()Landroid/content/ContentResolver;
    //   589: aload_0
    //   590: getfield 41	ob:f	Landroid/content/Context;
    //   593: iconst_4
    //   594: invokestatic 372	com/duapps/ad/stats/DuAdCacheProvider:a	(Landroid/content/Context;I)Landroid/net/Uri;
    //   597: ldc_w 470
    //   600: iconst_1
    //   601: anewarray 125	java/lang/String
    //   604: dup
    //   605: iconst_0
    //   606: lload 16
    //   608: invokestatic 219	java/lang/String:valueOf	(J)Ljava/lang/String;
    //   611: aastore
    //   612: invokevirtual 474	android/content/ContentResolver:delete	(Landroid/net/Uri;Ljava/lang/String;[Ljava/lang/String;)I
    //   615: pop
    //   616: new 168	java/lang/StringBuilder
    //   619: dup
    //   620: ldc_w 476
    //   623: invokespecial 173	java/lang/StringBuilder:<init>	(Ljava/lang/String;)V
    //   626: aload 11
    //   628: invokevirtual 177	java/lang/StringBuilder:toString	()Ljava/lang/String;
    //   631: invokevirtual 176	java/lang/StringBuilder:append	(Ljava/lang/String;)Ljava/lang/StringBuilder;
    //   634: ldc_w 478
    //   637: invokevirtual 176	java/lang/StringBuilder:append	(Ljava/lang/String;)Ljava/lang/StringBuilder;
    //   640: invokevirtual 177	java/lang/StringBuilder:toString	()Ljava/lang/String;
    //   643: astore_1
    //   644: aload_0
    //   645: getfield 41	ob:f	Landroid/content/Context;
    //   648: invokevirtual 367	android/content/Context:getContentResolver	()Landroid/content/ContentResolver;
    //   651: aload_0
    //   652: getfield 41	ob:f	Landroid/content/Context;
    //   655: iconst_4
    //   656: invokestatic 372	com/duapps/ad/stats/DuAdCacheProvider:a	(Landroid/content/Context;I)Landroid/net/Uri;
    //   659: aload_1
    //   660: aconst_null
    //   661: invokevirtual 474	android/content/ContentResolver:delete	(Landroid/net/Uri;Ljava/lang/String;[Ljava/lang/String;)I
    //   664: istore 14
    //   666: ldc 166
    //   668: new 168	java/lang/StringBuilder
    //   671: dup
    //   672: ldc_w 480
    //   675: invokespecial 173	java/lang/StringBuilder:<init>	(Ljava/lang/String;)V
    //   678: iload 14
    //   680: invokevirtual 307	java/lang/StringBuilder:append	(I)Ljava/lang/StringBuilder;
    //   683: invokevirtual 177	java/lang/StringBuilder:toString	()Ljava/lang/String;
    //   686: invokestatic 182	mv:c	(Ljava/lang/String;Ljava/lang/String;)V
    //   689: aload_0
    //   690: getfield 41	ob:f	Landroid/content/Context;
    //   693: ldc 241
    //   695: lconst_1
    //   696: lload 18
    //   698: ladd
    //   699: invokestatic 483	na:a	(Landroid/content/Context;Ljava/lang/String;J)V
    //   702: goto -537 -> 165
    //   705: astore_1
    //   706: invokestatic 310	mv:a	()Z
    //   709: ifeq -544 -> 165
    //   712: ldc 166
    //   714: ldc_w 485
    //   717: aload_1
    //   718: invokestatic 318	mv:a	(Ljava/lang/String;Ljava/lang/String;Ljava/lang/Throwable;)V
    //   721: goto -556 -> 165
    //   724: astore 7
    //   726: aconst_null
    //   727: astore_3
    //   728: aconst_null
    //   729: astore_2
    //   730: aconst_null
    //   731: astore_1
    //   732: iconst_0
    //   733: istore 14
    //   735: aload_3
    //   736: astore 4
    //   738: ldc 166
    //   740: ldc_w 382
    //   743: aload 7
    //   745: invokestatic 318	mv:a	(Ljava/lang/String;Ljava/lang/String;Ljava/lang/Throwable;)V
    //   748: aload_3
    //   749: ifnull +164 -> 913
    //   752: aload_3
    //   753: invokeinterface 412 1 0
    //   758: ifne +155 -> 913
    //   761: aload_3
    //   762: invokeinterface 415 1 0
    //   767: iconst_1
    //   768: istore 15
    //   770: goto -248 -> 522
    //   773: astore_1
    //   774: aconst_null
    //   775: astore 4
    //   777: aload 4
    //   779: ifnull +20 -> 799
    //   782: aload 4
    //   784: invokeinterface 412 1 0
    //   789: ifne +10 -> 799
    //   792: aload 4
    //   794: invokeinterface 415 1 0
    //   799: aload_1
    //   800: athrow
    //   801: aload_0
    //   802: iconst_0
    //   803: putfield 39	ob:a	I
    //   806: goto -614 -> 192
    //   809: aload_0
    //   810: getfield 62	ob:g	Landroid/os/Handler;
    //   813: iconst_4
    //   814: invokevirtual 392	android/os/Handler:removeMessages	(I)V
    //   817: aload_0
    //   818: getfield 62	ob:g	Landroid/os/Handler;
    //   821: iconst_3
    //   822: invokevirtual 66	android/os/Handler:sendEmptyMessage	(I)Z
    //   825: pop
    //   826: aload_0
    //   827: getfield 62	ob:g	Landroid/os/Handler;
    //   830: iconst_4
    //   831: ldc2_w 486
    //   834: invokevirtual 85	android/os/Handler:sendEmptyMessageDelayed	(IJ)Z
    //   837: pop
    //   838: iconst_1
    //   839: ireturn
    //   840: aload_0
    //   841: getfield 62	ob:g	Landroid/os/Handler;
    //   844: iconst_5
    //   845: invokevirtual 392	android/os/Handler:removeMessages	(I)V
    //   848: aload_0
    //   849: getfield 41	ob:f	Landroid/content/Context;
    //   852: invokestatic 490	np:b	(Landroid/content/Context;)Z
    //   855: ifeq +17 -> 872
    //   858: invokestatic 495	mm:a	()Lmm;
    //   861: new 497	oc
    //   864: dup
    //   865: aload_0
    //   866: invokespecial 500	oc:<init>	(Lob;)V
    //   869: invokevirtual 503	mm:a	(Ljava/lang/Runnable;)V
    //   872: aload_0
    //   873: getfield 62	ob:g	Landroid/os/Handler;
    //   876: iconst_5
    //   877: ldc2_w 80
    //   880: invokevirtual 85	android/os/Handler:sendEmptyMessageDelayed	(IJ)Z
    //   883: pop
    //   884: iconst_1
    //   885: ireturn
    //   886: astore_1
    //   887: goto -110 -> 777
    //   890: astore 7
    //   892: aconst_null
    //   893: astore_2
    //   894: aconst_null
    //   895: astore_1
    //   896: iconst_0
    //   897: istore 14
    //   899: goto -164 -> 735
    //   902: astore 7
    //   904: aload 6
    //   906: astore_2
    //   907: aload 5
    //   909: astore_1
    //   910: goto -175 -> 735
    //   913: iconst_1
    //   914: istore 15
    //   916: goto -394 -> 522
    //   919: iconst_0
    //   920: istore 15
    //   922: goto -400 -> 522
    //   925: aload_2
    //   926: astore 8
    //   928: aload_2
    //   929: ifnonnull -572 -> 357
    //   932: aload 10
    //   934: astore 8
    //   936: goto -579 -> 357
    //
    // Exception table:
    //   from	to	target	type
    //   582	702	705	java/lang/Exception
    //   73	142	724	java/lang/Exception
    //   73	142	773	finally
    //   197	206	886	finally
    //   209	215	886	finally
    //   240	246	886	finally
    //   262	271	886	finally
    //   280	289	886	finally
    //   298	307	886	finally
    //   316	325	886	finally
    //   334	343	886	finally
    //   374	384	886	finally
    //   401	411	886	finally
    //   422	448	886	finally
    //   459	473	886	finally
    //   494	500	886	finally
    //   738	748	886	finally
    //   197	206	890	java/lang/Exception
    //   209	215	890	java/lang/Exception
    //   240	246	890	java/lang/Exception
    //   262	271	902	java/lang/Exception
    //   280	289	902	java/lang/Exception
    //   298	307	902	java/lang/Exception
    //   316	325	902	java/lang/Exception
    //   334	343	902	java/lang/Exception
    //   374	384	902	java/lang/Exception
    //   401	411	902	java/lang/Exception
    //   422	448	902	java/lang/Exception
    //   459	473	902	java/lang/Exception
    //   494	500	902	java/lang/Exception
  }
}

/* Location:           classes-dex2jar.jar
 * Qualified Name:     ob
 * JD-Core Version:    0.6.2
 */