package cmcm.com.myapplication;

import android.content.Context;
import android.database.sqlite.SQLiteDatabase;

class on
{
  public static SQLiteDatabase a(Context paramContext)
  {
    try
    {
      paramContext = new om(paramContext).getReadableDatabase();
      return paramContext;
    }
    catch (Exception paramContext)
    {
      or.a(paramContext);
    }
    return null;
  }

  // ERROR //
  public static void a(Context paramContext, long paramLong1, long paramLong2, String paramString)
  {
    // Byte code:
    //   0: ldc 2
    //   2: monitorenter
    //   3: aload_0
    //   4: invokestatic 29	on:a	(Landroid/content/Context;)Landroid/database/sqlite/SQLiteDatabase;
    //   7: astore_0
    //   8: aload_0
    //   9: ldc 31
    //   11: iconst_3
    //   12: anewarray 4	java/lang/Object
    //   15: dup
    //   16: iconst_0
    //   17: lload_3
    //   18: invokestatic 37	java/lang/Long:valueOf	(J)Ljava/lang/Long;
    //   21: aastore
    //   22: dup
    //   23: iconst_1
    //   24: lload_1
    //   25: invokestatic 37	java/lang/Long:valueOf	(J)Ljava/lang/Long;
    //   28: aastore
    //   29: dup
    //   30: iconst_2
    //   31: aload 5
    //   33: aastore
    //   34: invokevirtual 43	android/database/sqlite/SQLiteDatabase:execSQL	(Ljava/lang/String;[Ljava/lang/Object;)V
    //   37: aload_0
    //   38: ifnull +7 -> 45
    //   41: aload_0
    //   42: invokevirtual 47	android/database/sqlite/SQLiteDatabase:close	()V
    //   45: ldc 2
    //   47: monitorexit
    //   48: return
    //   49: astore 5
    //   51: aload 5
    //   53: invokestatic 23	or:a	(Ljava/lang/Throwable;)V
    //   56: aload_0
    //   57: ifnull -12 -> 45
    //   60: aload_0
    //   61: invokevirtual 47	android/database/sqlite/SQLiteDatabase:close	()V
    //   64: goto -19 -> 45
    //   67: astore_0
    //   68: ldc 2
    //   70: monitorexit
    //   71: aload_0
    //   72: athrow
    //   73: astore 5
    //   75: aload_0
    //   76: ifnull +7 -> 83
    //   79: aload_0
    //   80: invokevirtual 47	android/database/sqlite/SQLiteDatabase:close	()V
    //   83: aload 5
    //   85: athrow
    //
    // Exception table:
    //   from	to	target	type
    //   8	37	49	android/database/SQLException
    //   3	8	67	finally
    //   41	45	67	finally
    //   60	64	67	finally
    //   79	83	67	finally
    //   83	86	67	finally
    //   8	37	73	finally
    //   51	56	73	finally
  }

  // ERROR //
  public static void a(Context paramContext, java.util.List<os> paramList)
  {
    // Byte code:
    //   0: ldc 2
    //   2: monitorenter
    //   3: aload_0
    //   4: invokestatic 29	on:a	(Landroid/content/Context;)Landroid/database/sqlite/SQLiteDatabase;
    //   7: astore_0
    //   8: aload_1
    //   9: invokeinterface 54 1 0
    //   14: astore_1
    //   15: aload_1
    //   16: invokeinterface 60 1 0
    //   21: ifeq +90 -> 111
    //   24: aload_1
    //   25: invokeinterface 64 1 0
    //   30: checkcast 66	os
    //   33: astore_2
    //   34: aload_0
    //   35: ldc 68
    //   37: iconst_5
    //   38: anewarray 4	java/lang/Object
    //   41: dup
    //   42: iconst_0
    //   43: aload_2
    //   44: getfield 71	os:a	J
    //   47: invokestatic 37	java/lang/Long:valueOf	(J)Ljava/lang/Long;
    //   50: aastore
    //   51: dup
    //   52: iconst_1
    //   53: aload_2
    //   54: getfield 74	os:b	J
    //   57: invokestatic 37	java/lang/Long:valueOf	(J)Ljava/lang/Long;
    //   60: aastore
    //   61: dup
    //   62: iconst_2
    //   63: aload_2
    //   64: getfield 77	os:c	J
    //   67: invokestatic 37	java/lang/Long:valueOf	(J)Ljava/lang/Long;
    //   70: aastore
    //   71: dup
    //   72: iconst_3
    //   73: aload_2
    //   74: getfield 80	os:d	J
    //   77: invokestatic 37	java/lang/Long:valueOf	(J)Ljava/lang/Long;
    //   80: aastore
    //   81: dup
    //   82: iconst_4
    //   83: aload_2
    //   84: getfield 84	os:e	Ljava/lang/String;
    //   87: aastore
    //   88: invokevirtual 43	android/database/sqlite/SQLiteDatabase:execSQL	(Ljava/lang/String;[Ljava/lang/Object;)V
    //   91: goto -76 -> 15
    //   94: astore_1
    //   95: aload_1
    //   96: invokestatic 23	or:a	(Ljava/lang/Throwable;)V
    //   99: aload_0
    //   100: ifnull +7 -> 107
    //   103: aload_0
    //   104: invokevirtual 47	android/database/sqlite/SQLiteDatabase:close	()V
    //   107: ldc 2
    //   109: monitorexit
    //   110: return
    //   111: aload_0
    //   112: ifnull -5 -> 107
    //   115: aload_0
    //   116: invokevirtual 47	android/database/sqlite/SQLiteDatabase:close	()V
    //   119: goto -12 -> 107
    //   122: astore_0
    //   123: ldc 2
    //   125: monitorexit
    //   126: aload_0
    //   127: athrow
    //   128: astore_1
    //   129: aload_0
    //   130: ifnull +7 -> 137
    //   133: aload_0
    //   134: invokevirtual 47	android/database/sqlite/SQLiteDatabase:close	()V
    //   137: aload_1
    //   138: athrow
    //
    // Exception table:
    //   from	to	target	type
    //   8	15	94	android/database/SQLException
    //   15	91	94	android/database/SQLException
    //   3	8	122	finally
    //   103	107	122	finally
    //   115	119	122	finally
    //   133	137	122	finally
    //   137	139	122	finally
    //   8	15	128	finally
    //   15	91	128	finally
    //   95	99	128	finally
  }

  // ERROR //
  public static boolean a(Context paramContext, String paramString)
  {
    // Byte code:
    //   0: aconst_null
    //   1: astore_2
    //   2: ldc 2
    //   4: monitorenter
    //   5: aload_0
    //   6: invokestatic 29	on:a	(Landroid/content/Context;)Landroid/database/sqlite/SQLiteDatabase;
    //   9: astore_3
    //   10: aload_3
    //   11: ldc 89
    //   13: iconst_1
    //   14: anewarray 91	java/lang/String
    //   17: dup
    //   18: iconst_0
    //   19: ldc 93
    //   21: aastore
    //   22: ldc 95
    //   24: iconst_1
    //   25: anewarray 91	java/lang/String
    //   28: dup
    //   29: iconst_0
    //   30: aload_1
    //   31: aastore
    //   32: aconst_null
    //   33: aconst_null
    //   34: aconst_null
    //   35: invokevirtual 99	android/database/sqlite/SQLiteDatabase:query	(Ljava/lang/String;[Ljava/lang/String;Ljava/lang/String;[Ljava/lang/String;Ljava/lang/String;Ljava/lang/String;Ljava/lang/String;)Landroid/database/Cursor;
    //   38: astore_1
    //   39: aload_1
    //   40: astore_0
    //   41: aload_1
    //   42: invokeinterface 104 1 0
    //   47: ifeq +132 -> 179
    //   50: aload_1
    //   51: astore_0
    //   52: aload_1
    //   53: iconst_0
    //   54: invokeinterface 108 2 0
    //   59: istore 4
    //   61: aload_1
    //   62: ifnull +9 -> 71
    //   65: aload_1
    //   66: invokeinterface 109 1 0
    //   71: aload_3
    //   72: ifnull +104 -> 176
    //   75: aload_3
    //   76: invokevirtual 47	android/database/sqlite/SQLiteDatabase:close	()V
    //   79: iload 4
    //   81: ifne +71 -> 152
    //   84: iconst_1
    //   85: istore 5
    //   87: ldc 2
    //   89: monitorexit
    //   90: iload 5
    //   92: ireturn
    //   93: astore_2
    //   94: aconst_null
    //   95: astore_1
    //   96: aload_1
    //   97: astore_0
    //   98: aload_2
    //   99: invokestatic 23	or:a	(Ljava/lang/Throwable;)V
    //   102: aload_1
    //   103: ifnull +9 -> 112
    //   106: aload_1
    //   107: invokeinterface 109 1 0
    //   112: aload_3
    //   113: ifnull +57 -> 170
    //   116: aload_3
    //   117: invokevirtual 47	android/database/sqlite/SQLiteDatabase:close	()V
    //   120: iconst_m1
    //   121: istore 4
    //   123: goto -44 -> 79
    //   126: aload_1
    //   127: ifnull +9 -> 136
    //   130: aload_1
    //   131: invokeinterface 109 1 0
    //   136: aload_3
    //   137: ifnull +7 -> 144
    //   140: aload_3
    //   141: invokevirtual 47	android/database/sqlite/SQLiteDatabase:close	()V
    //   144: aload_0
    //   145: athrow
    //   146: astore_0
    //   147: ldc 2
    //   149: monitorexit
    //   150: aload_0
    //   151: athrow
    //   152: iconst_0
    //   153: istore 5
    //   155: goto -68 -> 87
    //   158: astore_2
    //   159: aload_0
    //   160: astore_1
    //   161: aload_2
    //   162: astore_0
    //   163: goto -37 -> 126
    //   166: astore_2
    //   167: goto -71 -> 96
    //   170: iconst_m1
    //   171: istore 4
    //   173: goto -94 -> 79
    //   176: goto -97 -> 79
    //   179: iconst_m1
    //   180: istore 4
    //   182: goto -121 -> 61
    //   185: astore_0
    //   186: aload_2
    //   187: astore_1
    //   188: goto -62 -> 126
    //
    // Exception table:
    //   from	to	target	type
    //   10	39	93	java/lang/Exception
    //   5	10	146	finally
    //   65	71	146	finally
    //   75	79	146	finally
    //   106	112	146	finally
    //   116	120	146	finally
    //   130	136	146	finally
    //   140	144	146	finally
    //   144	146	146	finally
    //   41	50	158	finally
    //   52	61	158	finally
    //   98	102	158	finally
    //   41	50	166	java/lang/Exception
    //   52	61	166	java/lang/Exception
    //   10	39	185	finally
  }

  // ERROR //
  public static java.util.List<os> b(Context paramContext, String paramString)
  {
    // Byte code:
    //   0: ldc 2
    //   2: monitorenter
    //   3: aload_0
    //   4: invokestatic 29	on:a	(Landroid/content/Context;)Landroid/database/sqlite/SQLiteDatabase;
    //   7: astore_2
    //   8: aconst_null
    //   9: astore_0
    //   10: aload_2
    //   11: ldc 112
    //   13: iconst_1
    //   14: anewarray 91	java/lang/String
    //   17: dup
    //   18: iconst_0
    //   19: aload_1
    //   20: aastore
    //   21: invokevirtual 116	android/database/sqlite/SQLiteDatabase:rawQuery	(Ljava/lang/String;[Ljava/lang/String;)Landroid/database/Cursor;
    //   24: astore_1
    //   25: aload_1
    //   26: astore_0
    //   27: new 118	java/util/ArrayList
    //   30: dup
    //   31: invokespecial 120	java/util/ArrayList:<init>	()V
    //   34: astore_1
    //   35: aload_0
    //   36: invokeinterface 123 1 0
    //   41: ifeq +85 -> 126
    //   44: aload_1
    //   45: new 66	os
    //   48: dup
    //   49: aload_0
    //   50: iconst_0
    //   51: invokeinterface 127 2 0
    //   56: aload_0
    //   57: iconst_1
    //   58: invokeinterface 127 2 0
    //   63: aload_0
    //   64: iconst_2
    //   65: invokeinterface 127 2 0
    //   70: aload_0
    //   71: iconst_3
    //   72: invokeinterface 127 2 0
    //   77: aload_0
    //   78: iconst_4
    //   79: invokeinterface 131 2 0
    //   84: invokespecial 134	os:<init>	(JJJJLjava/lang/String;)V
    //   87: invokeinterface 138 2 0
    //   92: pop
    //   93: goto -58 -> 35
    //   96: astore_1
    //   97: aload_1
    //   98: invokestatic 23	or:a	(Ljava/lang/Throwable;)V
    //   101: aload_0
    //   102: ifnull +9 -> 111
    //   105: aload_0
    //   106: invokeinterface 109 1 0
    //   111: aload_2
    //   112: ifnull +7 -> 119
    //   115: aload_2
    //   116: invokevirtual 47	android/database/sqlite/SQLiteDatabase:close	()V
    //   119: aconst_null
    //   120: astore_0
    //   121: ldc 2
    //   123: monitorexit
    //   124: aload_0
    //   125: areturn
    //   126: aload_0
    //   127: ifnull +9 -> 136
    //   130: aload_0
    //   131: invokeinterface 109 1 0
    //   136: aload_1
    //   137: astore_0
    //   138: aload_2
    //   139: ifnull -18 -> 121
    //   142: aload_2
    //   143: invokevirtual 47	android/database/sqlite/SQLiteDatabase:close	()V
    //   146: aload_1
    //   147: astore_0
    //   148: goto -27 -> 121
    //   151: astore_0
    //   152: ldc 2
    //   154: monitorexit
    //   155: aload_0
    //   156: athrow
    //   157: astore_1
    //   158: aconst_null
    //   159: astore_0
    //   160: aload_0
    //   161: ifnull +9 -> 170
    //   164: aload_0
    //   165: invokeinterface 109 1 0
    //   170: aload_2
    //   171: ifnull +7 -> 178
    //   174: aload_2
    //   175: invokevirtual 47	android/database/sqlite/SQLiteDatabase:close	()V
    //   178: aload_1
    //   179: athrow
    //   180: astore_1
    //   181: goto -21 -> 160
    //   184: astore_1
    //   185: goto -25 -> 160
    //   188: astore_1
    //   189: goto -92 -> 97
    //
    // Exception table:
    //   from	to	target	type
    //   27	35	96	java/lang/Exception
    //   35	93	96	java/lang/Exception
    //   3	8	151	finally
    //   105	111	151	finally
    //   115	119	151	finally
    //   130	136	151	finally
    //   142	146	151	finally
    //   164	170	151	finally
    //   174	178	151	finally
    //   178	180	151	finally
    //   10	25	157	finally
    //   27	35	180	finally
    //   35	93	180	finally
    //   97	101	184	finally
    //   10	25	188	java/lang/Exception
  }

  // ERROR //
  public static void c(Context paramContext, String paramString)
  {
    // Byte code:
    //   0: ldc 2
    //   2: monitorenter
    //   3: aload_0
    //   4: invokestatic 29	on:a	(Landroid/content/Context;)Landroid/database/sqlite/SQLiteDatabase;
    //   7: astore_0
    //   8: aload_0
    //   9: ldc 89
    //   11: ldc 142
    //   13: iconst_1
    //   14: anewarray 91	java/lang/String
    //   17: dup
    //   18: iconst_0
    //   19: aload_1
    //   20: aastore
    //   21: invokevirtual 146	android/database/sqlite/SQLiteDatabase:delete	(Ljava/lang/String;Ljava/lang/String;[Ljava/lang/String;)I
    //   24: pop
    //   25: aload_0
    //   26: ifnull +7 -> 33
    //   29: aload_0
    //   30: invokevirtual 47	android/database/sqlite/SQLiteDatabase:close	()V
    //   33: ldc 2
    //   35: monitorexit
    //   36: return
    //   37: astore_1
    //   38: aload_1
    //   39: invokestatic 23	or:a	(Ljava/lang/Throwable;)V
    //   42: aload_0
    //   43: ifnull -10 -> 33
    //   46: aload_0
    //   47: invokevirtual 47	android/database/sqlite/SQLiteDatabase:close	()V
    //   50: goto -17 -> 33
    //   53: astore_0
    //   54: ldc 2
    //   56: monitorexit
    //   57: aload_0
    //   58: athrow
    //   59: astore_1
    //   60: aload_0
    //   61: ifnull +7 -> 68
    //   64: aload_0
    //   65: invokevirtual 47	android/database/sqlite/SQLiteDatabase:close	()V
    //   68: aload_1
    //   69: athrow
    //
    // Exception table:
    //   from	to	target	type
    //   8	25	37	java/lang/Exception
    //   3	8	53	finally
    //   29	33	53	finally
    //   46	50	53	finally
    //   64	68	53	finally
    //   68	70	53	finally
    //   8	25	59	finally
    //   38	42	59	finally
  }
}

/* Location:           classes-dex2jar.jar
 * Qualified Name:     on
 * JD-Core Version:    0.6.2
 */