package cmcm.com.myapplication;

class op extends Thread
{
  private os b;
  private boolean c;

  public op(oo paramoo, os paramos)
  {
    this.b = paramos;
  }

  public void a()
  {
    this.c = true;
  }

  // ERROR //
  public void run()
  {
    // Byte code:
    //   0: aconst_null
    //   1: astore_3
    //   2: aconst_null
    //   3: astore_1
    //   4: aconst_null
    //   5: astore 6
    //   7: iconst_0
    //   8: istore 9
    //   10: new 31	java/net/URL
    //   13: dup
    //   14: aload_0
    //   15: getfield 14	op:a	Loo;
    //   18: invokestatic 36	oo:b	(Loo;)Ljava/lang/String;
    //   21: invokespecial 39	java/net/URL:<init>	(Ljava/lang/String;)V
    //   24: invokevirtual 43	java/net/URL:openConnection	()Ljava/net/URLConnection;
    //   27: checkcast 45	java/net/HttpURLConnection
    //   30: astore_2
    //   31: aload_2
    //   32: sipush 5000
    //   35: invokevirtual 49	java/net/HttpURLConnection:setConnectTimeout	(I)V
    //   38: aload_2
    //   39: ldc 51
    //   41: invokevirtual 54	java/net/HttpURLConnection:setRequestMethod	(Ljava/lang/String;)V
    //   44: aload_2
    //   45: ldc 56
    //   47: new 58	java/lang/StringBuilder
    //   50: dup
    //   51: invokespecial 59	java/lang/StringBuilder:<init>	()V
    //   54: ldc 61
    //   56: invokevirtual 65	java/lang/StringBuilder:append	(Ljava/lang/String;)Ljava/lang/StringBuilder;
    //   59: aload_0
    //   60: getfield 19	op:b	Los;
    //   63: getfield 70	os:b	J
    //   66: aload_0
    //   67: getfield 19	op:b	Los;
    //   70: getfield 73	os:d	J
    //   73: ladd
    //   74: invokevirtual 76	java/lang/StringBuilder:append	(J)Ljava/lang/StringBuilder;
    //   77: ldc 78
    //   79: invokevirtual 65	java/lang/StringBuilder:append	(Ljava/lang/String;)Ljava/lang/StringBuilder;
    //   82: aload_0
    //   83: getfield 19	op:b	Los;
    //   86: getfield 80	os:c	J
    //   89: invokevirtual 76	java/lang/StringBuilder:append	(J)Ljava/lang/StringBuilder;
    //   92: invokevirtual 84	java/lang/StringBuilder:toString	()Ljava/lang/String;
    //   95: invokevirtual 88	java/net/HttpURLConnection:setRequestProperty	(Ljava/lang/String;Ljava/lang/String;)V
    //   98: new 90	java/io/RandomAccessFile
    //   101: dup
    //   102: new 58	java/lang/StringBuilder
    //   105: dup
    //   106: invokespecial 59	java/lang/StringBuilder:<init>	()V
    //   109: aload_0
    //   110: getfield 14	op:a	Loo;
    //   113: invokestatic 92	oo:c	(Loo;)Ljava/lang/String;
    //   116: invokevirtual 65	java/lang/StringBuilder:append	(Ljava/lang/String;)Ljava/lang/StringBuilder;
    //   119: ldc 94
    //   121: invokevirtual 65	java/lang/StringBuilder:append	(Ljava/lang/String;)Ljava/lang/StringBuilder;
    //   124: invokevirtual 84	java/lang/StringBuilder:toString	()Ljava/lang/String;
    //   127: ldc 96
    //   129: invokespecial 98	java/io/RandomAccessFile:<init>	(Ljava/lang/String;Ljava/lang/String;)V
    //   132: astore_3
    //   133: aload_3
    //   134: aload_0
    //   135: getfield 19	op:b	Los;
    //   138: getfield 70	os:b	J
    //   141: aload_0
    //   142: getfield 19	op:b	Los;
    //   145: getfield 73	os:d	J
    //   148: ladd
    //   149: invokevirtual 102	java/io/RandomAccessFile:seek	(J)V
    //   152: aload_2
    //   153: invokevirtual 106	java/net/HttpURLConnection:getInputStream	()Ljava/io/InputStream;
    //   156: astore 4
    //   158: aload_2
    //   159: astore_1
    //   160: aload_3
    //   161: astore_2
    //   162: aload 4
    //   164: astore_3
    //   165: aload_3
    //   166: ifnonnull +110 -> 276
    //   169: iconst_m1
    //   170: istore 10
    //   172: iload 10
    //   174: istore 9
    //   176: aload_1
    //   177: ifnull +18 -> 195
    //   180: aload_3
    //   181: astore 6
    //   183: aload_2
    //   184: astore 5
    //   186: aload_1
    //   187: astore 4
    //   189: aload_1
    //   190: invokevirtual 110	java/net/HttpURLConnection:getResponseCode	()I
    //   193: istore 9
    //   195: aload_3
    //   196: astore 6
    //   198: aload_2
    //   199: astore 5
    //   201: aload_1
    //   202: astore 4
    //   204: aload_0
    //   205: getfield 14	op:a	Loo;
    //   208: bipush 6
    //   210: iload 9
    //   212: invokestatic 113	oo:a	(Loo;II)V
    //   215: aload_1
    //   216: ifnull +7 -> 223
    //   219: aload_1
    //   220: invokevirtual 116	java/net/HttpURLConnection:disconnect	()V
    //   223: aload_3
    //   224: ifnull +7 -> 231
    //   227: aload_3
    //   228: invokevirtual 121	java/io/InputStream:close	()V
    //   231: aload_2
    //   232: ifnull +7 -> 239
    //   235: aload_2
    //   236: invokevirtual 122	java/io/RandomAccessFile:close	()V
    //   239: return
    //   240: astore 4
    //   242: aload_2
    //   243: astore_1
    //   244: aload_3
    //   245: astore_2
    //   246: aload 4
    //   248: astore_3
    //   249: aload_3
    //   250: invokestatic 127	or:a	(Ljava/lang/Throwable;)V
    //   253: ldc2_w 128
    //   256: invokestatic 132	java/lang/Thread:sleep	(J)V
    //   259: iload 9
    //   261: iconst_5
    //   262: if_icmplt +699 -> 961
    //   265: aconst_null
    //   266: astore_3
    //   267: goto -102 -> 165
    //   270: astore_1
    //   271: aload_1
    //   272: invokestatic 127	or:a	(Ljava/lang/Throwable;)V
    //   275: return
    //   276: aload_3
    //   277: astore 6
    //   279: aload_2
    //   280: astore 5
    //   282: aload_1
    //   283: astore 4
    //   285: sipush 4096
    //   288: newarray byte
    //   290: astore 7
    //   292: aload_3
    //   293: astore 6
    //   295: aload_2
    //   296: astore 5
    //   298: aload_1
    //   299: astore 4
    //   301: aload_3
    //   302: aload 7
    //   304: invokevirtual 136	java/io/InputStream:read	([B)I
    //   307: istore 9
    //   309: iload 9
    //   311: iconst_m1
    //   312: if_icmpeq +307 -> 619
    //   315: aload_3
    //   316: astore 6
    //   318: aload_2
    //   319: astore 5
    //   321: aload_1
    //   322: astore 4
    //   324: aload_2
    //   325: aload 7
    //   327: iconst_0
    //   328: iload 9
    //   330: invokevirtual 140	java/io/RandomAccessFile:write	([BII)V
    //   333: aload_3
    //   334: astore 6
    //   336: aload_2
    //   337: astore 5
    //   339: aload_1
    //   340: astore 4
    //   342: aload_0
    //   343: getfield 19	op:b	Los;
    //   346: astore 8
    //   348: aload_3
    //   349: astore 6
    //   351: aload_2
    //   352: astore 5
    //   354: aload_1
    //   355: astore 4
    //   357: aload 8
    //   359: aload 8
    //   361: getfield 73	os:d	J
    //   364: iload 9
    //   366: i2l
    //   367: ladd
    //   368: putfield 73	os:d	J
    //   371: aload_3
    //   372: astore 6
    //   374: aload_2
    //   375: astore 5
    //   377: aload_1
    //   378: astore 4
    //   380: aload_0
    //   381: getfield 22	op:c	Z
    //   384: istore 11
    //   386: iload 11
    //   388: ifeq +34 -> 422
    //   391: aload_1
    //   392: ifnull +7 -> 399
    //   395: aload_1
    //   396: invokevirtual 116	java/net/HttpURLConnection:disconnect	()V
    //   399: aload_3
    //   400: ifnull +7 -> 407
    //   403: aload_3
    //   404: invokevirtual 121	java/io/InputStream:close	()V
    //   407: aload_2
    //   408: ifnull -169 -> 239
    //   411: aload_2
    //   412: invokevirtual 122	java/io/RandomAccessFile:close	()V
    //   415: return
    //   416: astore_1
    //   417: aload_1
    //   418: invokestatic 127	or:a	(Ljava/lang/Throwable;)V
    //   421: return
    //   422: aload_3
    //   423: astore 6
    //   425: aload_2
    //   426: astore 5
    //   428: aload_1
    //   429: astore 4
    //   431: aload_0
    //   432: getfield 14	op:a	Loo;
    //   435: invokestatic 143	oo:d	(Loo;)Landroid/content/Context;
    //   438: aload_0
    //   439: getfield 19	op:b	Los;
    //   442: getfield 145	os:a	J
    //   445: aload_0
    //   446: getfield 19	op:b	Los;
    //   449: getfield 73	os:d	J
    //   452: aload_0
    //   453: getfield 14	op:a	Loo;
    //   456: invokestatic 36	oo:b	(Loo;)Ljava/lang/String;
    //   459: invokestatic 150	on:a	(Landroid/content/Context;JJLjava/lang/String;)V
    //   462: aload_3
    //   463: astore 6
    //   465: aload_2
    //   466: astore 5
    //   468: aload_1
    //   469: astore 4
    //   471: aload_0
    //   472: getfield 14	op:a	Loo;
    //   475: invokestatic 154	oo:e	(Loo;)Loq;
    //   478: ifnull +52 -> 530
    //   481: aload_3
    //   482: astore 6
    //   484: aload_2
    //   485: astore 5
    //   487: aload_1
    //   488: astore 4
    //   490: aload_0
    //   491: getfield 14	op:a	Loo;
    //   494: invokestatic 154	oo:e	(Loo;)Loq;
    //   497: aload_0
    //   498: getfield 14	op:a	Loo;
    //   501: aload_0
    //   502: getfield 14	op:a	Loo;
    //   505: invokestatic 36	oo:b	(Loo;)Ljava/lang/String;
    //   508: iload 9
    //   510: i2l
    //   511: aload_0
    //   512: getfield 14	op:a	Loo;
    //   515: invokestatic 157	oo:a	(Loo;)J
    //   518: aload_0
    //   519: getfield 14	op:a	Loo;
    //   522: invokestatic 161	oo:f	(Loo;)I
    //   525: invokeinterface 166 8 0
    //   530: aload_3
    //   531: astore 6
    //   533: aload_2
    //   534: astore 5
    //   536: aload_1
    //   537: astore 4
    //   539: aload_0
    //   540: getfield 14	op:a	Loo;
    //   543: invokestatic 169	oo:g	(Loo;)I
    //   546: iconst_4
    //   547: if_icmpeq +24 -> 571
    //   550: aload_3
    //   551: astore 6
    //   553: aload_2
    //   554: astore 5
    //   556: aload_1
    //   557: astore 4
    //   559: aload_0
    //   560: getfield 14	op:a	Loo;
    //   563: invokestatic 169	oo:g	(Loo;)I
    //   566: bipush 6
    //   568: if_icmpne -276 -> 292
    //   571: aload_3
    //   572: astore 6
    //   574: aload_2
    //   575: astore 5
    //   577: aload_1
    //   578: astore 4
    //   580: aload_0
    //   581: getfield 14	op:a	Loo;
    //   584: iconst_4
    //   585: invokestatic 172	oo:a	(Loo;I)V
    //   588: aload_1
    //   589: ifnull +7 -> 596
    //   592: aload_1
    //   593: invokevirtual 116	java/net/HttpURLConnection:disconnect	()V
    //   596: aload_3
    //   597: ifnull +7 -> 604
    //   600: aload_3
    //   601: invokevirtual 121	java/io/InputStream:close	()V
    //   604: aload_2
    //   605: ifnull -366 -> 239
    //   608: aload_2
    //   609: invokevirtual 122	java/io/RandomAccessFile:close	()V
    //   612: return
    //   613: astore_1
    //   614: aload_1
    //   615: invokestatic 127	or:a	(Ljava/lang/Throwable;)V
    //   618: return
    //   619: aload_3
    //   620: astore 6
    //   622: aload_2
    //   623: astore 5
    //   625: aload_1
    //   626: astore 4
    //   628: aload_0
    //   629: getfield 14	op:a	Loo;
    //   632: invokestatic 176	oo:h	(Loo;)V
    //   635: aload_1
    //   636: ifnull +7 -> 643
    //   639: aload_1
    //   640: invokevirtual 116	java/net/HttpURLConnection:disconnect	()V
    //   643: aload_3
    //   644: ifnull +7 -> 651
    //   647: aload_3
    //   648: invokevirtual 121	java/io/InputStream:close	()V
    //   651: aload_2
    //   652: ifnull -413 -> 239
    //   655: aload_2
    //   656: invokevirtual 122	java/io/RandomAccessFile:close	()V
    //   659: return
    //   660: astore_1
    //   661: aload_1
    //   662: invokestatic 127	or:a	(Ljava/lang/Throwable;)V
    //   665: return
    //   666: astore 4
    //   668: aload_3
    //   669: astore_1
    //   670: aconst_null
    //   671: astore 5
    //   673: aload_2
    //   674: astore_3
    //   675: aload 5
    //   677: astore_2
    //   678: aload 4
    //   680: invokestatic 127	or:a	(Ljava/lang/Throwable;)V
    //   683: aload_3
    //   684: ifnull +7 -> 691
    //   687: aload_3
    //   688: invokevirtual 116	java/net/HttpURLConnection:disconnect	()V
    //   691: aload_2
    //   692: ifnull +7 -> 699
    //   695: aload_2
    //   696: invokevirtual 121	java/io/InputStream:close	()V
    //   699: aload_1
    //   700: ifnull -461 -> 239
    //   703: aload_1
    //   704: invokevirtual 122	java/io/RandomAccessFile:close	()V
    //   707: return
    //   708: astore_1
    //   709: aload_1
    //   710: invokestatic 127	or:a	(Ljava/lang/Throwable;)V
    //   713: return
    //   714: astore 7
    //   716: aconst_null
    //   717: astore_3
    //   718: aload_3
    //   719: astore 6
    //   721: aload_2
    //   722: astore 5
    //   724: aload_1
    //   725: astore 4
    //   727: aload 7
    //   729: invokestatic 127	or:a	(Ljava/lang/Throwable;)V
    //   732: aload_1
    //   733: ifnull +7 -> 740
    //   736: aload_1
    //   737: invokevirtual 116	java/net/HttpURLConnection:disconnect	()V
    //   740: aload_3
    //   741: ifnull +7 -> 748
    //   744: aload_3
    //   745: invokevirtual 121	java/io/InputStream:close	()V
    //   748: aload_2
    //   749: ifnull -510 -> 239
    //   752: aload_2
    //   753: invokevirtual 122	java/io/RandomAccessFile:close	()V
    //   756: return
    //   757: astore_1
    //   758: aload_1
    //   759: invokestatic 127	or:a	(Ljava/lang/Throwable;)V
    //   762: return
    //   763: astore 4
    //   765: aload_3
    //   766: astore_1
    //   767: aload_2
    //   768: astore_3
    //   769: aload_1
    //   770: astore_2
    //   771: aload 4
    //   773: astore_1
    //   774: aload_3
    //   775: ifnull +7 -> 782
    //   778: aload_3
    //   779: invokevirtual 116	java/net/HttpURLConnection:disconnect	()V
    //   782: aload 6
    //   784: ifnull +8 -> 792
    //   787: aload 6
    //   789: invokevirtual 121	java/io/InputStream:close	()V
    //   792: aload_2
    //   793: ifnull +7 -> 800
    //   796: aload_2
    //   797: invokevirtual 122	java/io/RandomAccessFile:close	()V
    //   800: aload_1
    //   801: athrow
    //   802: astore_2
    //   803: aload_2
    //   804: invokestatic 127	or:a	(Ljava/lang/Throwable;)V
    //   807: goto -7 -> 800
    //   810: astore 4
    //   812: iload 10
    //   814: istore 9
    //   816: goto -621 -> 195
    //   819: astore 4
    //   821: aload_1
    //   822: astore_3
    //   823: aload 4
    //   825: astore_1
    //   826: goto -52 -> 774
    //   829: astore 4
    //   831: aload_1
    //   832: astore_2
    //   833: aload 4
    //   835: astore_1
    //   836: goto -62 -> 774
    //   839: astore 5
    //   841: aload_1
    //   842: astore_3
    //   843: aload_2
    //   844: astore 4
    //   846: aload 5
    //   848: astore_1
    //   849: aload_3
    //   850: astore_2
    //   851: aload 4
    //   853: astore_3
    //   854: goto -80 -> 774
    //   857: astore_1
    //   858: aload 5
    //   860: astore_2
    //   861: aload 4
    //   863: astore_3
    //   864: goto -90 -> 774
    //   867: astore 5
    //   869: aload_1
    //   870: astore 4
    //   872: aload 5
    //   874: astore_1
    //   875: aload_2
    //   876: astore 6
    //   878: aload 4
    //   880: astore_2
    //   881: goto -107 -> 774
    //   884: astore 7
    //   886: goto -168 -> 718
    //   889: astore 4
    //   891: aload_2
    //   892: astore 5
    //   894: aconst_null
    //   895: astore_2
    //   896: aload_1
    //   897: astore_3
    //   898: aload 5
    //   900: astore_1
    //   901: goto -223 -> 678
    //   904: astore 4
    //   906: aconst_null
    //   907: astore_2
    //   908: goto -230 -> 678
    //   911: astore 4
    //   913: aload_2
    //   914: astore_3
    //   915: aconst_null
    //   916: astore_2
    //   917: goto -239 -> 678
    //   920: astore 4
    //   922: aload_2
    //   923: astore 5
    //   925: aload_3
    //   926: astore_2
    //   927: aload_1
    //   928: astore_3
    //   929: aload 5
    //   931: astore_1
    //   932: goto -254 -> 678
    //   935: astore_2
    //   936: aload_3
    //   937: astore 4
    //   939: aload_2
    //   940: astore_3
    //   941: aload_1
    //   942: astore_2
    //   943: aload 4
    //   945: astore_1
    //   946: goto -697 -> 249
    //   949: astore_3
    //   950: aload_2
    //   951: astore 4
    //   953: aload_1
    //   954: astore_2
    //   955: aload 4
    //   957: astore_1
    //   958: goto -709 -> 249
    //   961: iload 9
    //   963: iconst_1
    //   964: iadd
    //   965: istore 9
    //   967: aload_1
    //   968: astore_3
    //   969: aload_2
    //   970: astore_1
    //   971: goto -961 -> 10
    //
    // Exception table:
    //   from	to	target	type
    //   133	158	240	java/io/IOException
    //   219	223	270	java/io/IOException
    //   227	231	270	java/io/IOException
    //   235	239	270	java/io/IOException
    //   395	399	416	java/io/IOException
    //   403	407	416	java/io/IOException
    //   411	415	416	java/io/IOException
    //   592	596	613	java/io/IOException
    //   600	604	613	java/io/IOException
    //   608	612	613	java/io/IOException
    //   639	643	660	java/io/IOException
    //   647	651	660	java/io/IOException
    //   655	659	660	java/io/IOException
    //   133	158	666	java/lang/InterruptedException
    //   687	691	708	java/io/IOException
    //   695	699	708	java/io/IOException
    //   703	707	708	java/io/IOException
    //   249	259	714	java/io/IOException
    //   736	740	757	java/io/IOException
    //   744	748	757	java/io/IOException
    //   752	756	757	java/io/IOException
    //   133	158	763	finally
    //   778	782	802	java/io/IOException
    //   787	792	802	java/io/IOException
    //   796	800	802	java/io/IOException
    //   189	195	810	java/lang/Exception
    //   249	259	819	finally
    //   10	31	829	finally
    //   31	133	839	finally
    //   189	195	857	finally
    //   204	215	857	finally
    //   285	292	857	finally
    //   301	309	857	finally
    //   324	333	857	finally
    //   342	348	857	finally
    //   357	371	857	finally
    //   380	386	857	finally
    //   431	462	857	finally
    //   471	481	857	finally
    //   490	530	857	finally
    //   539	550	857	finally
    //   559	571	857	finally
    //   580	588	857	finally
    //   628	635	857	finally
    //   727	732	857	finally
    //   678	683	867	finally
    //   189	195	884	java/io/IOException
    //   204	215	884	java/io/IOException
    //   285	292	884	java/io/IOException
    //   301	309	884	java/io/IOException
    //   324	333	884	java/io/IOException
    //   342	348	884	java/io/IOException
    //   357	371	884	java/io/IOException
    //   380	386	884	java/io/IOException
    //   431	462	884	java/io/IOException
    //   471	481	884	java/io/IOException
    //   490	530	884	java/io/IOException
    //   539	550	884	java/io/IOException
    //   559	571	884	java/io/IOException
    //   580	588	884	java/io/IOException
    //   628	635	884	java/io/IOException
    //   249	259	889	java/lang/InterruptedException
    //   10	31	904	java/lang/InterruptedException
    //   31	133	911	java/lang/InterruptedException
    //   189	195	920	java/lang/InterruptedException
    //   204	215	920	java/lang/InterruptedException
    //   285	292	920	java/lang/InterruptedException
    //   301	309	920	java/lang/InterruptedException
    //   324	333	920	java/lang/InterruptedException
    //   342	348	920	java/lang/InterruptedException
    //   357	371	920	java/lang/InterruptedException
    //   380	386	920	java/lang/InterruptedException
    //   431	462	920	java/lang/InterruptedException
    //   471	481	920	java/lang/InterruptedException
    //   490	530	920	java/lang/InterruptedException
    //   539	550	920	java/lang/InterruptedException
    //   559	571	920	java/lang/InterruptedException
    //   580	588	920	java/lang/InterruptedException
    //   628	635	920	java/lang/InterruptedException
    //   10	31	935	java/io/IOException
    //   31	133	949	java/io/IOException
  }
}

/* Location:           classes-dex2jar.jar
 * Qualified Name:     op
 * JD-Core Version:    0.6.2
 */