package cmcm.com.myapplication;

public class qo
{
  public static String a(String paramString)
  {
    return a(paramString, "GET", null);
  }

  // ERROR //
  public static String a(String paramString1, String paramString2, String paramString3)
  {
    // Byte code:
    //   0: aconst_null
    //   1: astore 4
    //   3: aconst_null
    //   4: astore 5
    //   6: aconst_null
    //   7: astore 6
    //   9: ldc 18
    //   11: new 20	java/lang/StringBuilder
    //   14: dup
    //   15: invokespecial 24	java/lang/StringBuilder:<init>	()V
    //   18: ldc 26
    //   20: invokevirtual 30	java/lang/StringBuilder:append	(Ljava/lang/String;)Ljava/lang/StringBuilder;
    //   23: aload_0
    //   24: invokevirtual 30	java/lang/StringBuilder:append	(Ljava/lang/String;)Ljava/lang/StringBuilder;
    //   27: ldc 32
    //   29: invokevirtual 30	java/lang/StringBuilder:append	(Ljava/lang/String;)Ljava/lang/StringBuilder;
    //   32: aload_1
    //   33: invokevirtual 30	java/lang/StringBuilder:append	(Ljava/lang/String;)Ljava/lang/StringBuilder;
    //   36: ldc 34
    //   38: invokevirtual 30	java/lang/StringBuilder:append	(Ljava/lang/String;)Ljava/lang/StringBuilder;
    //   41: aload_2
    //   42: invokevirtual 30	java/lang/StringBuilder:append	(Ljava/lang/String;)Ljava/lang/StringBuilder;
    //   45: invokevirtual 38	java/lang/StringBuilder:toString	()Ljava/lang/String;
    //   48: invokestatic 43	qq:a	(Ljava/lang/String;Ljava/lang/String;)V
    //   51: new 45	java/net/URL
    //   54: dup
    //   55: aload_0
    //   56: invokespecial 48	java/net/URL:<init>	(Ljava/lang/String;)V
    //   59: invokevirtual 52	java/net/URL:openConnection	()Ljava/net/URLConnection;
    //   62: checkcast 54	java/net/HttpURLConnection
    //   65: astore_0
    //   66: aload_0
    //   67: iconst_1
    //   68: invokevirtual 58	java/net/HttpURLConnection:setDoInput	(Z)V
    //   71: aload_0
    //   72: sipush 3000
    //   75: invokevirtual 62	java/net/HttpURLConnection:setConnectTimeout	(I)V
    //   78: aload_0
    //   79: sipush 5000
    //   82: invokevirtual 65	java/net/HttpURLConnection:setReadTimeout	(I)V
    //   85: aload_0
    //   86: aload_1
    //   87: invokevirtual 68	java/net/HttpURLConnection:setRequestMethod	(Ljava/lang/String;)V
    //   90: aload_2
    //   91: ifnull +466 -> 557
    //   94: aload_2
    //   95: invokevirtual 74	java/lang/String:isEmpty	()Z
    //   98: ifne +459 -> 557
    //   101: aload_0
    //   102: iconst_1
    //   103: invokevirtual 77	java/net/HttpURLConnection:setDoOutput	(Z)V
    //   106: aload_0
    //   107: invokevirtual 81	java/net/HttpURLConnection:getOutputStream	()Ljava/io/OutputStream;
    //   110: astore_1
    //   111: aload_1
    //   112: aload_2
    //   113: invokevirtual 85	java/lang/String:getBytes	()[B
    //   116: invokevirtual 91	java/io/OutputStream:write	([B)V
    //   119: aload_1
    //   120: invokevirtual 94	java/io/OutputStream:close	()V
    //   123: aload_1
    //   124: astore_2
    //   125: aload_0
    //   126: invokevirtual 98	java/net/HttpURLConnection:getResponseCode	()I
    //   129: istore 7
    //   131: ldc 100
    //   133: iload 7
    //   135: invokestatic 104	java/lang/String:valueOf	(I)Ljava/lang/String;
    //   138: invokestatic 43	qq:a	(Ljava/lang/String;Ljava/lang/String;)V
    //   141: aload_0
    //   142: invokevirtual 108	java/net/HttpURLConnection:getInputStream	()Ljava/io/InputStream;
    //   145: astore_3
    //   146: new 110	java/io/ByteArrayOutputStream
    //   149: dup
    //   150: invokespecial 111	java/io/ByteArrayOutputStream:<init>	()V
    //   153: astore_1
    //   154: sipush 1024
    //   157: newarray byte
    //   159: astore 4
    //   161: aload_3
    //   162: aload 4
    //   164: invokevirtual 117	java/io/InputStream:read	([B)I
    //   167: istore 8
    //   169: iload 8
    //   171: iconst_1
    //   172: if_icmplt +75 -> 247
    //   175: aload_1
    //   176: aload 4
    //   178: iconst_0
    //   179: iload 8
    //   181: invokevirtual 120	java/io/ByteArrayOutputStream:write	([BII)V
    //   184: goto -23 -> 161
    //   187: astore 5
    //   189: aload_0
    //   190: astore 4
    //   192: aload_1
    //   193: astore_0
    //   194: aload_2
    //   195: astore_1
    //   196: aload 4
    //   198: astore_2
    //   199: aload_3
    //   200: astore 4
    //   202: aload 5
    //   204: astore_3
    //   205: aload_3
    //   206: athrow
    //   207: astore 5
    //   209: aload_1
    //   210: astore_3
    //   211: aload_2
    //   212: astore_1
    //   213: aload_3
    //   214: astore_2
    //   215: aload 4
    //   217: astore_3
    //   218: aload_0
    //   219: astore 4
    //   221: aload 5
    //   223: astore_0
    //   224: aload 4
    //   226: invokestatic 125	qp:a	(Ljava/io/Closeable;)V
    //   229: aload_3
    //   230: invokestatic 125	qp:a	(Ljava/io/Closeable;)V
    //   233: aload_2
    //   234: invokestatic 125	qp:a	(Ljava/io/Closeable;)V
    //   237: aload_1
    //   238: ifnull +7 -> 245
    //   241: aload_1
    //   242: invokevirtual 128	java/net/HttpURLConnection:disconnect	()V
    //   245: aload_0
    //   246: athrow
    //   247: aload_1
    //   248: invokevirtual 129	java/io/ByteArrayOutputStream:toString	()Ljava/lang/String;
    //   251: astore 4
    //   253: ldc 131
    //   255: aload 4
    //   257: invokestatic 43	qq:a	(Ljava/lang/String;Ljava/lang/String;)V
    //   260: iload 7
    //   262: sipush 200
    //   265: if_icmpne +26 -> 291
    //   268: aload_1
    //   269: invokestatic 125	qp:a	(Ljava/io/Closeable;)V
    //   272: aload_3
    //   273: invokestatic 125	qp:a	(Ljava/io/Closeable;)V
    //   276: aload_2
    //   277: invokestatic 125	qp:a	(Ljava/io/Closeable;)V
    //   280: aload_0
    //   281: ifnull +7 -> 288
    //   284: aload_0
    //   285: invokevirtual 128	java/net/HttpURLConnection:disconnect	()V
    //   288: aload 4
    //   290: areturn
    //   291: new 14	pi
    //   294: dup
    //   295: iload 7
    //   297: new 16	java/lang/Throwable
    //   300: dup
    //   301: aload 4
    //   303: invokespecial 132	java/lang/Throwable:<init>	(Ljava/lang/String;)V
    //   306: invokespecial 135	pi:<init>	(ILjava/lang/Throwable;)V
    //   309: athrow
    //   310: astore 5
    //   312: aload_1
    //   313: astore 4
    //   315: aload_0
    //   316: astore_1
    //   317: aload 5
    //   319: astore_0
    //   320: new 14	pi
    //   323: dup
    //   324: aload_0
    //   325: invokespecial 138	pi:<init>	(Ljava/lang/Throwable;)V
    //   328: athrow
    //   329: astore_0
    //   330: goto -106 -> 224
    //   333: astore_0
    //   334: aconst_null
    //   335: astore_3
    //   336: aconst_null
    //   337: astore_2
    //   338: aconst_null
    //   339: astore_1
    //   340: goto -116 -> 224
    //   343: astore 5
    //   345: aconst_null
    //   346: astore_3
    //   347: aconst_null
    //   348: astore_2
    //   349: aload_0
    //   350: astore_1
    //   351: aload 5
    //   353: astore_0
    //   354: goto -130 -> 224
    //   357: astore 5
    //   359: aconst_null
    //   360: astore_3
    //   361: aload_1
    //   362: astore_2
    //   363: aload_0
    //   364: astore_1
    //   365: aload 5
    //   367: astore_0
    //   368: goto -144 -> 224
    //   371: astore 5
    //   373: aconst_null
    //   374: astore_3
    //   375: aload_0
    //   376: astore_1
    //   377: aload 5
    //   379: astore_0
    //   380: goto -156 -> 224
    //   383: astore 5
    //   385: aload_0
    //   386: astore_1
    //   387: aload 5
    //   389: astore_0
    //   390: goto -166 -> 224
    //   393: astore 5
    //   395: aload_1
    //   396: astore 4
    //   398: aload_0
    //   399: astore_1
    //   400: aload 5
    //   402: astore_0
    //   403: goto -179 -> 224
    //   406: astore_0
    //   407: aconst_null
    //   408: astore_3
    //   409: aconst_null
    //   410: astore_2
    //   411: aconst_null
    //   412: astore_1
    //   413: aload 5
    //   415: astore 4
    //   417: goto -97 -> 320
    //   420: astore 4
    //   422: aconst_null
    //   423: astore_3
    //   424: aconst_null
    //   425: astore_2
    //   426: aload_0
    //   427: astore_1
    //   428: aload 4
    //   430: astore_0
    //   431: aload 5
    //   433: astore 4
    //   435: goto -115 -> 320
    //   438: astore 4
    //   440: aconst_null
    //   441: astore_3
    //   442: aload_1
    //   443: astore_2
    //   444: aload_0
    //   445: astore_1
    //   446: aload 4
    //   448: astore_0
    //   449: aload 5
    //   451: astore 4
    //   453: goto -133 -> 320
    //   456: astore 4
    //   458: aconst_null
    //   459: astore_3
    //   460: aload_0
    //   461: astore_1
    //   462: aload 4
    //   464: astore_0
    //   465: aload 5
    //   467: astore 4
    //   469: goto -149 -> 320
    //   472: astore 4
    //   474: aload_0
    //   475: astore_1
    //   476: aload 4
    //   478: astore_0
    //   479: aload 5
    //   481: astore 4
    //   483: goto -163 -> 320
    //   486: astore_3
    //   487: aconst_null
    //   488: astore_0
    //   489: aconst_null
    //   490: astore_1
    //   491: aconst_null
    //   492: astore_2
    //   493: aload 6
    //   495: astore 4
    //   497: goto -292 -> 205
    //   500: astore_3
    //   501: aconst_null
    //   502: astore_1
    //   503: aload_0
    //   504: astore_2
    //   505: aconst_null
    //   506: astore_0
    //   507: aload 6
    //   509: astore 4
    //   511: goto -306 -> 205
    //   514: astore_3
    //   515: aload_0
    //   516: astore_2
    //   517: aconst_null
    //   518: astore_0
    //   519: aload 6
    //   521: astore 4
    //   523: goto -318 -> 205
    //   526: astore_3
    //   527: aload_2
    //   528: astore_1
    //   529: aload_0
    //   530: astore_2
    //   531: aconst_null
    //   532: astore_0
    //   533: aload 6
    //   535: astore 4
    //   537: goto -332 -> 205
    //   540: astore 5
    //   542: aload_2
    //   543: astore_1
    //   544: aload_3
    //   545: astore 4
    //   547: aload_0
    //   548: astore_2
    //   549: aload 5
    //   551: astore_3
    //   552: aconst_null
    //   553: astore_0
    //   554: goto -349 -> 205
    //   557: aconst_null
    //   558: astore_2
    //   559: goto -434 -> 125
    //
    // Exception table:
    //   from	to	target	type
    //   154	161	187	pi
    //   161	169	187	pi
    //   175	184	187	pi
    //   247	260	187	pi
    //   291	310	187	pi
    //   205	207	207	finally
    //   154	161	310	java/lang/Throwable
    //   161	169	310	java/lang/Throwable
    //   175	184	310	java/lang/Throwable
    //   247	260	310	java/lang/Throwable
    //   291	310	310	java/lang/Throwable
    //   320	329	329	finally
    //   51	66	333	finally
    //   66	90	343	finally
    //   94	111	343	finally
    //   111	123	357	finally
    //   125	146	371	finally
    //   146	154	383	finally
    //   154	161	393	finally
    //   161	169	393	finally
    //   175	184	393	finally
    //   247	260	393	finally
    //   291	310	393	finally
    //   51	66	406	java/lang/Throwable
    //   66	90	420	java/lang/Throwable
    //   94	111	420	java/lang/Throwable
    //   111	123	438	java/lang/Throwable
    //   125	146	456	java/lang/Throwable
    //   146	154	472	java/lang/Throwable
    //   51	66	486	pi
    //   66	90	500	pi
    //   94	111	500	pi
    //   111	123	514	pi
    //   125	146	526	pi
    //   146	154	540	pi
  }
}

/* Location:           classes-dex2jar.jar
 * Qualified Name:     qo
 * JD-Core Version:    0.6.2
 */